Workbook

Sheet INSTRUCCIONES
A1: CÓMO SE USA ESTA HOJA
A3: Regla única | B3: Las celdas amarillas se escriben a mano. Todo lo demás se calcula solo. Ningún precio, ningún total y ningún conteo se escribe nunca a mano.
A5: 1 · PEDIDO | B5: Llena la cabecera, el diseño, los colores con su código HEX y las ubicaciones con el texto exacto que va impreso. Abajo hay un panel de revisión que te avisa qué falta.
A6: 2 · PRENDAS | B6: Una fila por prenda física. La fila 3 es un ejemplo: escribe encima. La última columna te dice qué le falta a cada fila.
A7: 3 · PROFORMA | B7: Se llena sola. Inserta el mockup en el recuadro y registra el adelanto recibido. Es la página 1 del PDF.
A8: 4 · DETALLE | B8: Se llena solo. Es la página 2 del PDF, la que el cliente revisa y confirma.
A9: 5 · FICHA_DISENO | B9: Se llena sola. Es lo que recibe el diseñador. No tiene ni un solo precio.
A10: 6 · MEDIDAS | B10: La llena el diseñador después del nesting. De ahí sale el costo de impresión y el nombre de los archivos TIF.
A11: 7 · CATALOGOS | B11: Precios, recargos y parámetros. Solo lo toca el administrador.
A13: Para generar el PDF | B13: Selecciona las pestañas PROFORMA y DETALLE juntas y exporta a PDF. Para el diseñador, exporta FICHA_DISENO.
A15: Pendiente | B15: El RUC 20544457846 fue dictado por voz: verifícalo antes de usarlo con clientes. Los costos internos de tela y confección están en cero en CATÁLOGOS hasta que los completes.
A17: LEYENDA DE COLORES
A18: Amarillo | B18: Celda que se escribe a mano
A19: Sin fondo | B19: Celda calculada — no la toques
A20: Verde oscuro | B20: Encabezado de sección

Sheet CATALOGOS
A1: CATÁLOGOS — solo los modifica el administrador
A2: Todos los precios y recargos de la hoja salen de aquí. La vendedora nunca escribe un precio a mano.
A4: PRODUCTOS Y SUS COMPONENTES FÍSICOS
A5: Producto | B5: Precio base | C5: Camisetas | D5: Shorts | E5: Medias | F5: Nota
A6: Camiseta sola | B6: 25 | C6: 1 | D6: 0 | E6: 0 | F6: Matriz §3.1 — S/25 tallas S, M, L
A7: Camiseta + short | B7: 40 | C7: 1 | D7: 1 | E7: 0 | F7: Matriz §3.1 — no incluye medias
A8: Kit completo | B8: 45 | C8: 1 | D8: 1 | E8: 1 | F8: Matriz §3.1 — camiseta + short + medias
A9: Camiseta arquero | B9: 35 | C9: 1 | D9: 0 | E9: 0 | F9: Matriz §3.1 — desde S/60 el conjunto; verificar
A10: Conjunto arquero | B10: 60 | C10: 1 | D10: 1 | E10: 1 | F10: Matriz §3.1 — desde S/60
A11: Short solo | B11: 15 | C11: 0 | D11: 1 | E11: 0 | F11: Valor de la tarifa estándar del kit
A12: Medias | B12: 5 | C12: 0 | D12: 0 | E12: 1 | F12: Valor de la tarifa estándar del kit
A13: Falda deportiva | B13: 25 | C13: 1 | D13: 0 | E13: 0 | F13: Matriz §1 — tallas 6 a 16
A14: Banderola | B14: 25 | C14: 0 | D14: 0 | E14: 0 | F14: Precio observado en pedido real (CLINT)
A17: TALLAS Y RECARGOS
A18: Talla | B18: Recargo | C18: Tipo | F18: Nota
A19: 6 | B19: 0 | C19: Infantil
A20: 8 | B20: 0 | C20: Infantil
A21: 10 | B21: 0 | C21: Infantil
A22: 12 | B22: 0 | C22: Infantil
A23: 14 | B23: 0 | C23: Infantil
A24: 16 | B24: 0 | C24: Infantil
A25: S | B25: 0 | C25: Adulto
A26: M | B26: 0 | C26: Adulto
A27: L | B27: 0 | C27: Adulto
A28: XL | B28: 3 | C28: Adulto | F28: Matriz §3.2 — XL +3, XXL +6, XXXL +10
A29: XXL | B29: 6 | C29: Adulto
A30: XXXL | B30: 10 | C30: Adulto
A33: TELAS Y RECARGOS
A34: Tela | B34: Recargo | F34: Nota
A35: Dry Fit | B35: 0 | F35: Base — matriz §3.3
A36: Win Fresh | B36: 0 | F36: Base — matriz §3.3
A37: Marathon | B37: 5 | F37: +S/5 por camiseta
A38: Puma | B38: 5 | F38: +S/5 por camiseta
A39: Palmeira | B39: 5 | F39: +S/5 por camiseta
A40: Hexagonal | B40: 5 | F40: +S/5 por conjunto
A41: Labrada | B41: 10 | F41: +S/10 por prenda
A42: Nova sin forro | B42: 0 | F42: Tela de short
A45: CUELLOS Y RECARGOS
A46: Cuello | B46: Recargo | F46: Nota
A47: Redondo | B47: 0 | F47: Incluido
A48: Redondo cruzado | B48: 0 | F48: Incluido
A49: V | B49: 0 | F49: Incluido
A50: V cruzado | B50: 0 | F50: Incluido
A51: Camisero | B51: 10 | F51: Matriz §4 — +S/10 por camiseta
A54: ACABADOS Y RECARGOS
A55: Acabado | B55: Recargo | F55: Nota
A56: Sublimado | B56: 0 | F56: Incluido en el proceso
A57: Ninguno | B57: 0
A58: Termosellado | B58: 5 | F58: Matriz §4 — +S/5
A59: Bordado | B59: 5 | F59: Matriz §4 — +S/5
A60: DTF | B60: 5 | F60: Matriz §4 — +S/5
A61: Vinil | B61: 5 | F61: Matriz §4 — +S/5
A62: Parche | B62: 5 | F62: Matriz §4 — +S/5
A65: LISTAS DESPLEGABLES
A66: Género | B66: Corte | C66: Tipo de prenda | D66: Sí / No | E66: Manga | F66: Modalidad de entrega
A67: Hombre | B67: Recto | C67: Venta | D67: Sí | E67: Corta | F67: Recojo Surquillo
A68: Mujer | B68: Entallado | C68: Obsequio | D68: No | E68: Larga | F68: Recojo Gamarra
A69: Niño | B69: Princesa | C69: Muestra | F69: Motorizado Lima
A70: Niña | F70: Agencia a provincia
A71: Sin especificar
A74: PARÁMETROS COMERCIALES
A75: IGV | B75: 0.18 | F75: Matriz §13 — 18%, no incluido en los precios
A76: Adelanto estándar | B76: 0.5 | F76: Matriz §6 — 50% sin IGV
A77: Adelanto excepcional | B77: 0.4 | F77: Matriz §6 — 40%, requiere autorización
A78: Pedido mínimo (unidades) | B78: 12 | F78: Matriz §2
A79: Ancho de impresión (m) | B79: 1.8 | F79: Dato de taller — ancho fijo
A80: Costo impresión por metro lineal | B80: 8 | F80: Incluye impresión, calandra y corte láser
A81: Validez de la proforma (días) | B81: 7 | F81: Ajustable
A84: COSTOS INTERNOS — PENDIENTES DE COMPLETAR
A85: Estos valores no estaban en la matriz maestra. Complétalos para que la hoja calcule utilidad.
A86: Concepto | B86: Costo | C86: Unidad | F86: Nota
A87: Dry Fit | B87: 0 | C87: por metro lineal | F87: Pendiente
A88: Win Fresh | B88: 0 | C88: por metro lineal | F88: Pendiente
A89: Marathon | B89: 0 | C89: por metro lineal | F89: Pendiente
A90: Puma | B90: 0 | C90: por metro lineal | F90: Pendiente
A91: Palmeira | B91: 0 | C91: por metro lineal | F91: Pendiente
A92: Hexagonal | B92: 0 | C92: por metro lineal | F92: Pendiente
A93: Labrada | B93: 0 | C93: por metro lineal | F93: Pendiente
A94: Nova sin forro | B94: 0 | C94: por metro lineal | F94: Pendiente
A95: Confección camiseta | B95: 0 | C95: por prenda | F95: Pendiente — tarifa de costurero
A96: Confección short | B96: 0 | C96: por prenda | F96: Pendiente — tarifa de costurero
A97: Termosellado | B97: 0 | C97: por prenda | F97: Pendiente
A98: Bordado | B98: 0 | C98: por prenda | F98: Pendiente

Sheet PEDIDO
A1: DATOS DEL PEDIDO — esta es la hoja que llena la vendedora
A2: Las celdas amarillas se escriben. Todo lo demás se calcula solo. Las listas desplegables salen de CATÁLOGOS.
A4: 1 · IDENTIFICACIÓN
A5: N° de pedido | B5: SUB-000842 | E5: Fecha | F5: 2026-08-07
A6: Versión de la hoja | B6: 4 | E6: Fecha de esta versión | F6: 2026-08-07
A7: Cliente / Grupo | B7: PROMO 2002 | E7: RUC o DNI
A8: Coordinador del cliente | B8: Coordinador de la promoción | E8: Teléfono | F8: +51 966 826 524
A9: Vendedora | E9: Fecha de entrega | F9: 2026-08-18
A10: Modalidad de entrega | B10: Agencia a provincia | E10: Ciudad | F10: Chiclayo
A12: 2 · DISEÑO APROBADO
A13: Versión del mockup | B13: v4 | E13: Fecha de aprobación | F13: 2026-08-07
A14: Aprobado por | B14: Coordinador del cliente | E14: Archivo del mockup | F14: Aprobado por WhatsApp
A15: Tela principal | B15: Win Fresh | E15: Manga | F15: Corta
A16: Cuello — hombres | B16: Redondo | E16: Cuello — damas | F16: Redondo
A17: Corte — hombres | B17: Recto | E17: Corte — damas | F17: Entallado
A18: Rib en cuello | B18: Sí | E18: Rib en mangas | F18: No
A19: Acabado de escudos | B19: Sublimado | E19: Short — tela | F19: Win Fresh
A21: 3 · COLORES — nunca solo la palabra, siempre el código
A22: Nombre del color | B22: Código HEX | C22: Referencia física / Pantone
A23: Blanco hueso | B23: #F7F4F2 | C23: PENDIENTE — el pedido real nunca tuvo código
A24: Azul | B24: #2B4E7A | C24: PENDIENTE — el pedido real nunca tuvo código
A29: Tres de nueve pedidos reales fallaron por color acordado solo con una palabra. El único que no falló llevaba el código HEX.
A31: 4 · UBICACIONES Y TEXTO LITERAL — se copia y pega, nunca se vuelve a escribir
A32: Ubicación | B32: ¿Lleva? | C32: Contenido exacto que va impreso
A33: Pecho / delantero | B33: Sí | C33: Texto "PROMO 2002", insignia del colegio bordada y sponsors correspondientes
A34: Espalda | B34: Sí | C34: Nombre, número y sponsor
A35: Cuello delantero | B35: No
A36: Cuello posterior | B36: No
A37: Manga izquierda | B37: Sí | C37: Copa y texto "COPA 2026"
A38: Manga derecha | B38: Sí | C38: Insignia del campeonato
A39: Short delantero | B39: Sí | C39: Insignia del colegio lado derecho, número lado izquierdo
A40: Short posterior | B40: Sí | C40: Sponsors correspondientes
A41: Sponsor 1 — texto y teléfono | B41: Sí | C41: SIN DEFINIR — la confirmación real nunca dijo qué sponsor ni su teléfono
A42: Sponsor 2 — texto y teléfono | B42: No
A43: El teléfono de un auspiciador salió mal impreso porque nunca estuvo escrito en la confirmación. Todo lo que se imprime va aquí, literal.
A45: 5 · ENVÍO A PROVINCIA — los siete datos de rotulado
A46: Nombre completo
A47: DNI
A48: Celular
A49: Ciudad o destino
A50: Agencia
A51: Referencia de la agencia
A52: Correo electrónico
A54: 6 · CONTROL DE CAMBIOS
A55: Fecha | B55: Qué cambió | E55: Quién lo pidió | G55: Versión
A64: Un pedido real perdió una camiseta agregada al final porque la hoja no se actualizó. Cada cambio, una línea.
A66: 7 · REVISIÓN ANTES DE ENVIAR
A67: Prendas registradas | C67: =COUNTA(PRENDAS!$B$3:$B$202) -> 28 | D67: ="—" -> —
A68: Prendas de venta | C68: =COUNTIFS(PRENDAS!$O$3:$O$202,"Venta",PRENDAS!$B$3:$B$202,"<>") -> 28 | D68: ="—" -> —
A69: Sin nombre en prenda | C69: =COUNTIFS(PRENDAS!$D$3:$D$202,"<>",PRENDAS!$B$3:$B$202,"") -> 0 | D69: =IF(C69=0,"OK","REVISAR") -> OK
A70: Sin talla | C70: =COUNTIFS(PRENDAS!$B$3:$B$202,"<>",PRENDAS!$E$3:$E$202,"") -> 0 | D70: =IF(C70=0,"OK","REVISAR") -> OK
A71: Sin número | C71: =COUNTIFS(PRENDAS!$B$3:$B$202,"<>",PRENDAS!$F$3:$F$202,"") -> 0 | D71: =IF(C71=0,"OK","REVISAR") -> OK
A72: Sin género | C72: =COUNTIFS(PRENDAS!$B$3:$B$202,"<>",PRENDAS!$H$3:$H$202,"") -> 0 | D72: =IF(C72=0,"OK","REVISAR") -> OK
A73: Sin corte | C73: =COUNTIFS(PRENDAS!$B$3:$B$202,"<>",PRENDAS!$I$3:$I$202,"") -> 0 | D73: =IF(C73=0,"OK","REVISAR") -> OK
A74: Colores sin código HEX | C74: =COUNTIFS($A$23:$A$28,"<>",$B$23:$B$28,"") -> 0 | D74: =IF(C74=0,"OK","REVISAR") -> OK
A75: Ubicaciones marcadas sin contenido | C75: =COUNTIFS($B$33:$B$42,"Sí",$C$33:$C$42,"") -> 0 | D75: =IF(C75=0,"OK","REVISAR") -> OK
A76: Pedido mínimo | C76: =IF(C68<CATALOGOS!$B$78,"MENOR AL MÍNIMO","OK") -> OK
A77: Mockup aprobado | C77: =IF(F13="","FALTA FECHA DE APROBACIÓN","OK") -> OK

Sheet PRENDAS
A1: PRENDAS — una fila por prenda física. Todos los resúmenes salen de aquí. | AA1: ◀ La fila 3 es un ejemplo. Escribe encima.
A2: # | B2: Nombre en prenda | C2: Nombre de la persona | D2: Producto | E2: Talla | F2: Número | G2: Color | H2: Género | I2: Corte | J2: Cuello | K2: Tela | L2: Escudo | M2: Acabado escudo | N2: Arquero | O2: Tipo | P2: Personalización especial | Q2: Precio base | R2: Rec. talla | S2: Rec. tela | T2: Rec. cuello | U2: Rec. acabado | V2: PRECIO UNIT. | W2: Camisetas | X2: Shorts | Y2: Medias | Z2: Qué falta
A3: =IF($B3="","",ROW()-2) -> 1 | B3: ANMIX BRENIS | C3: Luis Chapoñán Vera | D3: Kit completo | E3: M | F3: 7 | G3: Blanco hueso | H3: Hombre | I3: Recto | J3: Redondo | K3: Win Fresh | L3: Sí | M3: Sublimado | N3: No | O3: Venta | P3: Nombre de esposa en cuello delantero | Q3: {=IF($D3="","",IFERROR(INDEX(CATALOGOS!$B$6:$B$14,MATCH($D3,CATALOGOS!$A$6:$A$14,0)),0))} -> 45 | R3: {=IF($E3="",0,IFERROR(INDEX(CATALOGOS!$B$19:$B$30,MATCH($E3,CATALOGOS!$A$19:$A$30,0)),0))} -> 0 | S3: {=IF($K3="",0,IFERROR(INDEX(CATALOGOS!$B$35:$B$42,MATCH($K3,CATALOGOS!$A$35:$A$42,0)),0))} -> 0 | T3: {=IF($J3="",0,IFERROR(INDEX(CATALOGOS!$B$47:$B$51,MATCH($J3,CATALOGOS!$A$47:$A$51,0)),0))} -> 0 | U3: {=IF($M3="",0,IFERROR(INDEX(CATALOGOS!$B$56:$B$62,MATCH($M3,CATALOGOS!$A$56:$A$62,0)),0))} -> 0 | V3: =IF($B3="","",IF($O3="Venta",SUM($Q3:$U3),0)) -> 45 | W3: {=IF($D3="",0,IFERROR(INDEX(CATALOGOS!$C$6:$C$14,MATCH($D3,CATALOGOS!$A$6:$A$14,0)),0))} -> 1 | X3: {=IF($D3="",0,IFERROR(INDEX(CATALOGOS!$D$6:$D$14,MATCH($D3,CATALOGOS!$A$6:$A$14,0)),0))} -> 1 | Y3: {=IF($D3="",0,IFERROR(INDEX(CATALOGOS!$E$6:$E$14,MATCH($D3,CATALOGOS!$A$6:$A$14,0)),0))} -> 1 | Z3: =IF(COUNTA($B3:$P3)=0,"",IF($B3="","nombre. ","")&IF($D3="","producto. ","")&IF($E3="","talla. ","")&IF($F3="","número. ","")&IF($H3="","género. ","")&IF($I3="","corte. ","")&IF($O3="","tipo. ",""))
A4: =IF($B4="","",ROW()-2) -> 2 | B4: J. HUANCAS | D4: Kit completo | E4: M | F4: 7 | G4: Blanco hueso | H4: Hombre | I4: Recto | J4: Redondo | K4: Win Fresh | L4: Sí | M4: Sublimado | N4: No | O4: Venta | Q4: {=IF($D4="","",IFERROR(INDEX(CATALOGOS!$B$6:$B$14,MATCH($D4,CATALOGOS!$A$6:$A$14,0)),0))} -> 45 | R4: {=IF($E4="",0,IFERROR(INDEX(CATALOGOS!$B$19:$B$30,MATCH($E4,CATALOGOS!$A$19:$A$30,0)),0))} -> 0 | S4: {=IF($K4="",0,IFERROR(INDEX(CATALOGOS!$B$35:$B$42,MATCH($K4,CATALOGOS!$A$35:$A$42,0)),0))} -> 0 | T4: {=IF($J4="",0,IFERROR(INDEX(CATALOGOS!$B$47:$B$51,MATCH($J4,CATALOGOS!$A$47:$A$51,0)),0))} -> 0 | U4: {=IF($M4="",0,IFERROR(INDEX(CATALOGOS!$B$56:$B$62,MATCH($M4,CATALOGOS!$A$56:$A$62,0)),0))} -> 0 | V4: =IF($B4="","",IF($O4="Venta",SUM($Q4:$U4),0)) -> 45 | W4: {=IF($D4="",0,IFERROR(INDEX(CATALOGOS!$C$6:$C$14,MATCH($D4,CATALOGOS!$A$6:$A$14,0)),0))} -> 1 | X4: {=IF($D4="",0,IFERROR(INDEX(CATALOGOS!$D$6:$D$14,MATCH($D4,CATALOGOS!$A$6:$A$14,0)),0))} -> 1 | Y4: {=IF($D4="",0,IFERROR(INDEX(CATALOGOS!$E$6:$E$14,MATCH($D4,CATALOGOS!$A$6:$A$14,0)),0))} -> 1 | Z4: =IF(COUNTA($B4:$P4)=0,"",IF($B4="","nombre. ","")&IF($D4="","producto. ","")&IF($E4="","talla. ","")&IF($F4="","número. ","")&IF($H4="","género. ","")&IF($I4="","corte. ","")&IF($O4="","tipo. ",""))
A5: =IF($B5="","",ROW()-2) -> 3 | B5: BANCES | D5: Kit completo | E5: M | F5: 17 | G5: Blanco hueso | H5: Hombre | I5: Recto | J5: Redondo | K5: Win Fresh | L5: Sí | M5: Sublimado | N5: No | O5: Venta | Q5: {=IF($D5="","",IFERROR(INDEX(CATALOGOS!$B$6:$B$14,MATCH($D5,CATALOGOS!$A$6:$A$14,0)),0))} -> 45 | R5: {=IF($E5="",0,IFERROR(INDEX(CATALOGOS!$B$19:$B$30,MATCH($E5,CATALOGOS!$A$19:$A$30,0)),0))} -> 0 | S5: {=IF($K5="",0,IFERROR(INDEX(CATALOGOS!$B$35:$B$42,MATCH($K5,CATALOGOS!$A$35:$A$42,0)),0))} -> 0 | T5: {=IF($J5="",0,IFERROR(INDEX(CATALOGOS!$B$47:$B$51,MATCH($J5,CATALOGOS!$A$47:$A$51,0)),0))} -> 0 | U5: {=IF($M5="",0,IFERROR(INDEX(CATALOGOS!$B$56:$B$62,MATCH($M5,CATALOGOS!$A$56:$A$62,0)),0))} -> 0 | V5: =IF($B5="","",IF($O5="Venta",SUM($Q5:$U5),0)) -> 45 | W5: {=IF($D5="",0,IFERROR(INDEX(CATALOGOS!$C$6:$C$14,MATCH($D5,CATALOGOS!$A$6:$A$14,0)),0))} -> 1 | X5: {=IF($D5="",0,IFERROR(INDEX(CATALOGOS!$D$6:$D$14,MATCH($D5,CATALOGOS!$A$6:$A$14,0)),0))} -> 1 | Y5: {=IF($D5="",0,IFERROR(INDEX(CATALOGOS!$E$6:$E$14,MATCH($D5,CATALOGOS!$A$6:$A$14,0)),0))} -> 1 | Z5: =IF(COUNTA($B5:$P5)=0,"",IF($B5="","nombre. ","")&IF($D5="","producto. ","")&IF($E5="","talla. ","")&IF($F5="","número. ","")&IF($H5="","género. ","")&IF($I5="","corte. ","")&IF($O5="","tipo. ",""))
A6: =IF($B6="","",ROW()-2) -> 4 | B6: VENTURA | D6: Kit completo | E6: M | F6: 9 | G6: Blanco hueso | H6: Hombre | I6: Recto | J6: Redondo | K6: Win Fresh | L6: Sí | M6: Sublimado | N6: No | O6: Venta | Q6: {=IF($D6="","",IFERROR(INDEX(CATALOGOS!$B$6:$B$14,MATCH($D6,CATALOGOS!$A$6:$A$14,0)),0))} -> 45 | R6: {=IF($E6="",0,IFERROR(INDEX(CATALOGOS!$B$19:$B$30,MATCH($E6,CATALOGOS!$A$19:$A$30,0)),0))} -> 0 | S6: {=IF($K6="",0,IFERROR(INDEX(CATALOGOS!$B$35:$B$42,MATCH($K6,CATALOGOS!$A$35:$A$42,0)),0))} -> 0 | T6: {=IF($J6="",0,IFERROR(INDEX(CATALOGOS!$B$47:$B$51,MATCH($J6,CATALOGOS!$A$47:$A$51,0)),0))} -> 0 | U6: {=IF($M6="",0,IFERROR(INDEX(CATALOGOS!$B$56:$B$62,MATCH($M6,CATALOGOS!$A$56:$A$62,0)),0))} -> 0 | V6: =IF($B6="","",IF($O6="Venta",SUM($Q6:$U6),0)) -> 45 | W6: {=IF($D6="",0,IFERROR(INDEX(CATALOGOS!$C$6:$C$14,MATCH($D6,CATALOGOS!$A$6:$A$14,0)),0))} -> 1 | X6: {=IF($D6="",0,IFERROR(INDEX(CATALOGOS!$D$6:$D$14,MATCH($D6,CATALOGOS!$A$6:$A$14,0)),0))} -> 1 | Y6: {=IF($D6="",0,IFERROR(INDEX(CATALOGOS!$E$6:$E$14,MATCH($D6,CATALOGOS!$A$6:$A$14,0)),0))} -> 1 | Z6: =IF(COUNTA($B6:$P6)=0,"",IF($B6="","nombre. ","")&IF($D6="","producto. ","")&IF($E6="","talla. ","")&IF($F6="","número. ","")&IF($H6="","género. ","")&IF($I6="","corte. ","")&IF($O6="","tipo. ",""))
A7: =IF($B7="","",ROW()-2) -> 5 | B7: JHEINER | D7: Kit completo | E7: M | F7: 12 | G7: Blanco hueso | H7: Hombre | I7: Recto | J7: Redondo | K7: Win Fresh | L7: Sí | M7: Sublimado | N7: No | O7: Venta | Q7: {=IF($D7="","",IFERROR(INDEX(CATALOGOS!$B$6:$B$14,MATCH($D7,CATALOGOS!$A$6:$A$14,0)),0))} -> 45 | R7: {=IF($E7="",0,IFERROR(INDEX(CATALOGOS!$B$19:$B$30,MATCH($E7,CATALOGOS!$A$19:$A$30,0)),0))} -> 0 | S7: {=IF($K7="",0,IFERROR(INDEX(CATALOGOS!$B$35:$B$42,MATCH($K7,CATALOGOS!$A$35:$A$42,0)),0))} -> 0 | T7: {=IF($J7="",0,IFERROR(INDEX(CATALOGOS!$B$47:$B$51,MATCH($J7,CATALOGOS!$A$47:$A$51,0)),0))} -> 0 | U7: {=IF($M7="",0,IFERROR(INDEX(CATALOGOS!$B$56:$B$62,MATCH($M7,CATALOGOS!$A$56:$A$62,0)),0))} -> 0 | V7: =IF($B7="","",IF($O7="Venta",SUM($Q7:$U7),0)) -> 45 | W7: {=IF($D7="",0,IFERROR(INDEX(CATALOGOS!$C$6:$C$14,MATCH($D7,CATALOGOS!$A$6:$A$14,0)),0))} -> 1 | X7: {=IF($D7="",0,IFERROR(INDEX(CATALOGOS!$D$6:$D$14,MATCH($D7,CATALOGOS!$A$6:$A$14,0)),0))} -> 1 | Y7: {=IF($D7="",0,IFERROR(INDEX(CATALOGOS!$E$6:$E$14,MATCH($D7,CATALOGOS!$A$6:$A$14,0)),0))} -> 1 | Z7: =IF(COUNTA($B7:$P7)=0,"",IF($B7="","nombre. ","")&IF($D7="","producto. ","")&IF($E7="","talla. ","")&IF($F7="","número. ","")&IF($H7="","género. ","")&IF($I7="","corte. ","")&IF($O7="","tipo. ",""))
A8: =IF($B8="","",ROW()-2) -> 6 | B8: JUAN R. | D8: Kit completo | E8: M | F8: 12 | G8: Blanco hueso | H8: Hombre | I8: Recto | J8: Redondo | K8: Win Fresh | L8: Sí | M8: Sublimado | N8: No | O8: Venta | P8: JUAN R. nombre principal; KALESSI en cuello delantero; JOHNATAN manga izquierda; DIEGO manga derecha | Q8: {=IF($D8="","",IFERROR(INDEX(CATALOGOS!$B$6:$B$14,MATCH($D8,CATALOGOS!$A$6:$A$14,0)),0))} -> 45 | R8: {=IF($E8="",0,IFERROR(INDEX(CATALOGOS!$B$19:$B$30,MATCH($E8,CATALOGOS!$A$19:$A$30,0)),0))} -> 0 | S8: {=IF($K8="",0,IFERROR(INDEX(CATALOGOS!$B$35:$B$42,MATCH($K8,CATALOGOS!$A$35:$A$42,0)),0))} -> 0 | T8: {=IF($J8="",0,IFERROR(INDEX(CATALOGOS!$B$47:$B$51,MATCH($J8,CATALOGOS!$A$47:$A$51,0)),0))} -> 0 | U8: {=IF($M8="",0,IFERROR(INDEX(CATALOGOS!$B$56:$B$62,MATCH($M8,CATALOGOS!$A$56:$A$62,0)),0))} -> 0 | V8: =IF($B8="","",IF($O8="Venta",SUM($Q8:$U8),0)) -> 45 | W8: {=IF($D8="",0,IFERROR(INDEX(CATALOGOS!$C$6:$C$14,MATCH($D8,CATALOGOS!$A$6:$A$14,0)),0))} -> 1 | X8: {=IF($D8="",0,IFERROR(INDEX(CATALOGOS!$D$6:$D$14,MATCH($D8,CATALOGOS!$A$6:$A$14,0)),0))} -> 1 | Y8: {=IF($D8="",0,IFERROR(INDEX(CATALOGOS!$E$6:$E$14,MATCH($D8,CATALOGOS!$A$6:$A$14,0)),0))} -> 1 | Z8: =IF(COUNTA($B8:$P8)=0,"",IF($B8="","nombre. ","")&IF($D8="","producto. ","")&IF($E8="","talla. ","")&IF($F8="","número. ","")&IF($H8="","género. ","")&IF($I8="","corte. ","")&IF($O8="","tipo. ",""))
A9: =IF($B9="","",ROW()-2) -> 7 | B9: JORGE C. | D9: Kit completo | E9: M | F9: 7 | G9: Blanco hueso | H9: Hombre | I9: Recto | J9: Redondo | K9: Win Fresh | L9: Sí | M9: Sublimado | N9: No | O9: Venta | Q9: {=IF($D9="","",IFERROR(INDEX(CATALOGOS!$B$6:$B$14,MATCH($D9,CATALOGOS!$A$6:$A$14,0)),0))} -> 45 | R9: {=IF($E9="",0,IFERROR(INDEX(CATALOGOS!$B$19:$B$30,MATCH($E9,CATALOGOS!$A$19:$A$30,0)),0))} -> 0 | S9: {=IF($K9="",0,IFERROR(INDEX(CATALOGOS!$B$35:$B$42,MATCH($K9,CATALOGOS!$A$35:$A$42,0)),0))} -> 0 | T9: {=IF($J9="",0,IFERROR(INDEX(CATALOGOS!$B$47:$B$51,MATCH($J9,CATALOGOS!$A$47:$A$51,0)),0))} -> 0 | U9: {=IF($M9="",0,IFERROR(INDEX(CATALOGOS!$B$56:$B$62,MATCH($M9,CATALOGOS!$A$56:$A$62,0)),0))} -> 0 | V9: =IF($B9="","",IF($O9="Venta",SUM($Q9:$U9),0)) -> 45 | W9: {=IF($D9="",0,IFERROR(INDEX(CATALOGOS!$C$6:$C$14,MATCH($D9,CATALOGOS!$A$6:$A$14,0)),0))} -> 1 | X9: {=IF($D9="",0,IFERROR(INDEX(CATALOGOS!$D$6:$D$14,MATCH($D9,CATALOGOS!$A$6:$A$14,0)),0))} -> 1 | Y9: {=IF($D9="",0,IFERROR(INDEX(CATALOGOS!$E$6:$E$14,MATCH($D9,CATALOGOS!$A$6:$A$14,0)),0))} -> 1 | Z9: =IF(COUNTA($B9:$P9)=0,"",IF($B9="","nombre. ","")&IF($D9="","producto. ","")&IF($E9="","talla. ","")&IF($F9="","número. ","")&IF($H9="","género. ","")&IF($I9="","corte. ","")&IF($O9="","tipo. ",""))
A10: =IF($B10="","",ROW()-2) -> 8 | B10: C. ACOSTA | D10: Kit completo | E10: M | F10: 10 | G10: Blanco hueso | H10: Hombre | I10: Recto | J10: Redondo | K10: Win Fresh | L10: Sí | M10: Sublimado | N10: No | O10: Venta | Q10: {=IF($D10="","",IFERROR(INDEX(CATALOGOS!$B$6:$B$14,MATCH($D10,CATALOGOS!$A$6:$A$14,0)),0))} -> 45 | R10: {=IF($E10="",0,IFERROR(INDEX(CATALOGOS!$B$19:$B$30,MATCH($E10,CATALOGOS!$A$19:$A$30,0)),0))} -> 0 | S10: {=IF($K10="",0,IFERROR(INDEX(CATALOGOS!$B$35:$B$42,MATCH($K10,CATALOGOS!$A$35:$A$42,0)),0))} -> 0 | T10: {=IF($J10="",0,IFERROR(INDEX(CATALOGOS!$B$47:$B$51,MATCH($J10,CATALOGOS!$A$47:$A$51,0)),0))} -> 0 | U10: {=IF($M10="",0,IFERROR(INDEX(CATALOGOS!$B$56:$B$62,MATCH($M10,CATALOGOS!$A$56:$A$62,0)),0))} -> 0 | V10: =IF($B10="","",IF($O10="Venta",SUM($Q10:$U10),0)) -> 45 | W10: {=IF($D10="",0,IFERROR(INDEX(CATALOGOS!$C$6:$C$14,MATCH($D10,CATALOGOS!$A$6:$A$14,0)),0))} -> 1 | X10: {=IF($D10="",0,IFERROR(INDEX(CATALOGOS!$D$6:$D$14,MATCH($D10,CATALOGOS!$A$6:$A$14,0)),0))} -> 1 | Y10: {=IF($D10="",0,IFERROR(INDEX(CATALOGOS!$E$6:$E$14,MATCH($D10,CATALOGOS!$A$6:$A$14,0)),0))} -> 1 | Z10: =IF(COUNTA($B10:$P10)=0,"",IF($B10="","nombre. ","")&IF($D10="","producto. ","")&IF($E10="","talla. ","")&IF($F10="","número. ","")&IF($H10="","género. ","")&IF($I10="","corte. ","")&IF($O10="","tipo. ",""))
A11: =IF($B11="","",ROW()-2) -> 9 | B11: LADINES | D11: Kit completo | E11: L | F11: 3 | G11: Blanco hueso | H11: Hombre | I11: Recto | J11: Redondo | K11: Win Fresh | L11: Sí | M11: Sublimado | N11: No | O11: Venta | Q11: {=IF($D11="","",IFERROR(INDEX(CATALOGOS!$B$6:$B$14,MATCH($D11,CATALOGOS!$A$6:$A$14,0)),0))} -> 45 | R11: {=IF($E11="",0,IFERROR(INDEX(CATALOGOS!$B$19:$B$30,MATCH($E11,CATALOGOS!$A$19:$A$30,0)),0))} -> 0 | S11: {=IF($K11="",0,IFERROR(INDEX(CATALOGOS!$B$35:$B$42,MATCH($K11,CATALOGOS!$A$35:$A$42,0)),0))} -> 0 | T11: {=IF($J11="",0,IFERROR(INDEX(CATALOGOS!$B$47:$B$51,MATCH($J11,CATALOGOS!$A$47:$A$51,0)),0))} -> 0 | U11: {=IF($M11="",0,IFERROR(INDEX(CATALOGOS!$B$56:$B$62,MATCH($M11,CATALOGOS!$A$56:$A$62,0)),0))} -> 0 | V11: =IF($B11="","",IF($O11="Venta",SUM($Q11:$U11),0)) -> 45 | W11: {=IF($D11="",0,IFERROR(INDEX(CATALOGOS!$C$6:$C$14,MATCH($D11,CATALOGOS!$A$6:$A$14,0)),0))} -> 1 | X11: {=IF($D11="",0,IFERROR(INDEX(CATALOGOS!$D$6:$D$14,MATCH($D11,CATALOGOS!$A$6:$A$14,0)),0))} -> 1 | Y11: {=IF($D11="",0,IFERROR(INDEX(CATALOGOS!$E$6:$E$14,MATCH($D11,CATALOGOS!$A$6:$A$14,0)),0))} -> 1 | Z11: =IF(COUNTA($B11:$P11)=0,"",IF($B11="","nombre. ","")&IF($D11="","producto. ","")&IF($E11="","talla. ","")&IF($F11="","número. ","")&IF($H11="","género. ","")&IF($I11="","corte. ","")&IF($O11="","tipo. ",""))
A12: =IF($B12="","",ROW()-2) -> 10 | B12: GUSTAVO R. | D12: Kit completo | E12: L | F12: 11 | G12: Blanco hueso | H12: Hombre | I12: Recto | J12: Redondo | K12: Win Fresh | L12: Sí | M12: Sublimado | N12: No | O12: Venta | Q12: {=IF($D12="","",IFERROR(INDEX(CATALOGOS!$B$6:$B$14,MATCH($D12,CATALOGOS!$A$6:$A$14,0)),0))} -> 45 | R12: {=IF($E12="",0,IFERROR(INDEX(CATALOGOS!$B$19:$B$30,MATCH($E12,CATALOGOS!$A$19:$A$30,0)),0))} -> 0 | S12: {=IF($K12="",0,IFERROR(INDEX(CATALOGOS!$B$35:$B$42,MATCH($K12,CATALOGOS!$A$35:$A$42,0)),0))} -> 0 | T12: {=IF($J12="",0,IFERROR(INDEX(CATALOGOS!$B$47:$B$51,MATCH($J12,CATALOGOS!$A$47:$A$51,0)),0))} -> 0 | U12: {=IF($M12="",0,IFERROR(INDEX(CATALOGOS!$B$56:$B$62,MATCH($M12,CATALOGOS!$A$56:$A$62,0)),0))} -> 0 | V12: =IF($B12="","",IF($O12="Venta",SUM($Q12:$U12),0)) -> 45 | W12: {=IF($D12="",0,IFERROR(INDEX(CATALOGOS!$C$6:$C$14,MATCH($D12,CATALOGOS!$A$6:$A$14,0)),0))} -> 1 | X12: {=IF($D12="",0,IFERROR(INDEX(CATALOGOS!$D$6:$D$14,MATCH($D12,CATALOGOS!$A$6:$A$14,0)),0))} -> 1 | Y12: {=IF($D12="",0,IFERROR(INDEX(CATALOGOS!$E$6:$E$14,MATCH($D12,CATALOGOS!$A$6:$A$14,0)),0))} -> 1 | Z12: =IF(COUNTA($B12:$P12)=0,"",IF($B12="","nombre. ","")&IF($D12="","producto. ","")&IF($E12="","talla. ","")&IF($F12="","número. ","")&IF($H12="","género. ","")&IF($I12="","corte. ","")&IF($O12="","tipo. ",""))
A13: =IF($B13="","",ROW()-2) -> 11 | B13: CALDERON | D13: Kit completo | E13: L | F13: 14 | G13: Blanco hueso | H13: Hombre | I13: Recto | J13: Redondo | K13: Win Fresh | L13: Sí | M13: Sublimado | N13: No | O13: Venta | Q13: {=IF($D13="","",IFERROR(INDEX(CATALOGOS!$B$6:$B$14,MATCH($D13,CATALOGOS!$A$6:$A$14,0)),0))} -> 45 | R13: {=IF($E13="",0,IFERROR(INDEX(CATALOGOS!$B$19:$B$30,MATCH($E13,CATALOGOS!$A$19:$A$30,0)),0))} -> 0 | S13: {=IF($K13="",0,IFERROR(INDEX(CATALOGOS!$B$35:$B$42,MATCH($K13,CATALOGOS!$A$35:$A$42,0)),0))} -> 0 | T13: {=IF($J13="",0,IFERROR(INDEX(CATALOGOS!$B$47:$B$51,MATCH($J13,CATALOGOS!$A$47:$A$51,0)),0))} -> 0 | U13: {=IF($M13="",0,IFERROR(INDEX(CATALOGOS!$B$56:$B$62,MATCH($M13,CATALOGOS!$A$56:$A$62,0)),0))} -> 0 | V13: =IF($B13="","",IF($O13="Venta",SUM($Q13:$U13),0)) -> 45 | W13: {=IF($D13="",0,IFERROR(INDEX(CATALOGOS!$C$6:$C$14,MATCH($D13,CATALOGOS!$A$6:$A$14,0)),0))} -> 1 | X13: {=IF($D13="",0,IFERROR(INDEX(CATALOGOS!$D$6:$D$14,MATCH($D13,CATALOGOS!$A$6:$A$14,0)),0))} -> 1 | Y13: {=IF($D13="",0,IFERROR(INDEX(CATALOGOS!$E$6:$E$14,MATCH($D13,CATALOGOS!$A$6:$A$14,0)),0))} -> 1 | Z13: =IF(COUNTA($B13:$P13)=0,"",IF($B13="","nombre. ","")&IF($D13="","producto. ","")&IF($E13="","talla. ","")&IF($F13="","número. ","")&IF($H13="","género. ","")&IF($I13="","corte. ","")&IF($O13="","tipo. ",""))
A14: =IF($B14="","",ROW()-2) -> 12 | B14: ALAN F. | D14: Kit completo | E14: L | F14: 8 | G14: Blanco hueso | H14: Hombre | I14: Recto | J14: Redondo | K14: Win Fresh | L14: Sí | M14: Sublimado | N14: No | O14: Venta | Q14: {=IF($D14="","",IFERROR(INDEX(CATALOGOS!$B$6:$B$14,MATCH($D14,CATALOGOS!$A$6:$A$14,0)),0))} -> 45 | R14: {=IF($E14="",0,IFERROR(INDEX(CATALOGOS!$B$19:$B$30,MATCH($E14,CATALOGOS!$A$19:$A$30,0)),0))} -> 0 | S14: {=IF($K14="",0,IFERROR(INDEX(CATALOGOS!$B$35:$B$42,MATCH($K14,CATALOGOS!$A$35:$A$42,0)),0))} -> 0 | T14: {=IF($J14="",0,IFERROR(INDEX(CATALOGOS!$B$47:$B$51,MATCH($J14,CATALOGOS!$A$47:$A$51,0)),0))} -> 0 | U14: {=IF($M14="",0,IFERROR(INDEX(CATALOGOS!$B$56:$B$62,MATCH($M14,CATALOGOS!$A$56:$A$62,0)),0))} -> 0 | V14: =IF($B14="","",IF($O14="Venta",SUM($Q14:$U14),0)) -> 45 | W14: {=IF($D14="",0,IFERROR(INDEX(CATALOGOS!$C$6:$C$14,MATCH($D14,CATALOGOS!$A$6:$A$14,0)),0))} -> 1 | X14: {=IF($D14="",0,IFERROR(INDEX(CATALOGOS!$D$6:$D$14,MATCH($D14,CATALOGOS!$A$6:$A$14,0)),0))} -> 1 | Y14: {=IF($D14="",0,IFERROR(INDEX(CATALOGOS!$E$6:$E$14,MATCH($D14,CATALOGOS!$A$6:$A$14,0)),0))} -> 1 | Z14: =IF(COUNTA($B14:$P14)=0,"",IF($B14="","nombre. ","")&IF($D14="","producto. ","")&IF($E14="","talla. ","")&IF($F14="","número. ","")&IF($H14="","género. ","")&IF($I14="","corte. ","")&IF($O14="","tipo. ",""))
A15: =IF($B15="","",ROW()-2) -> 13 | B15: ALAN R. | D15: Kit completo | E15: L | F15: 7 | G15: Blanco hueso | H15: Hombre | I15: Recto | J15: Redondo | K15: Win Fresh | L15: Sí | M15: Sublimado | N15: No | O15: Venta | Q15: {=IF($D15="","",IFERROR(INDEX(CATALOGOS!$B$6:$B$14,MATCH($D15,CATALOGOS!$A$6:$A$14,0)),0))} -> 45 | R15: {=IF($E15="",0,IFERROR(INDEX(CATALOGOS!$B$19:$B$30,MATCH($E15,CATALOGOS!$A$19:$A$30,0)),0))} -> 0 | S15: {=IF($K15="",0,IFERROR(INDEX(CATALOGOS!$B$35:$B$42,MATCH($K15,CATALOGOS!$A$35:$A$42,0)),0))} -> 0 | T15: {=IF($J15="",0,IFERROR(INDEX(CATALOGOS!$B$47:$B$51,MATCH($J15,CATALOGOS!$A$47:$A$51,0)),0))} -> 0 | U15: {=IF($M15="",0,IFERROR(INDEX(CATALOGOS!$B$56:$B$62,MATCH($M15,CATALOGOS!$A$56:$A$62,0)),0))} -> 0 | V15: =IF($B15="","",IF($O15="Venta",SUM($Q15:$U15),0)) -> 45 | W15: {=IF($D15="",0,IFERROR(INDEX(CATALOGOS!$C$6:$C$14,MATCH($D15,CATALOGOS!$A$6:$A$14,0)),0))} -> 1 | X15: {=IF($D15="",0,IFERROR(INDEX(CATALOGOS!$D$6:$D$14,MATCH($D15,CATALOGOS!$A$6:$A$14,0)),0))} -> 1 | Y15: {=IF($D15="",0,IFERROR(INDEX(CATALOGOS!$E$6:$E$14,MATCH($D15,CATALOGOS!$A$6:$A$14,0)),0))} -> 1 | Z15: =IF(COUNTA($B15:$P15)=0,"",IF($B15="","nombre. ","")&IF($D15="","producto. ","")&IF($E15="","talla. ","")&IF($F15="","número. ","")&IF($H15="","género. ","")&IF($I15="","corte. ","")&IF($O15="","tipo. ",""))
A16: =IF($B16="","",ROW()-2) -> 14 | B16: FLORES | D16: Kit completo | E16: L | F16: 30 | G16: Blanco hueso | H16: Hombre | I16: Recto | J16: Redondo | K16: Win Fresh | L16: Sí | M16: Sublimado | N16: No | O16: Venta | Q16: {=IF($D16="","",IFERROR(INDEX(CATALOGOS!$B$6:$B$14,MATCH($D16,CATALOGOS!$A$6:$A$14,0)),0))} -> 45 | R16: {=IF($E16="",0,IFERROR(INDEX(CATALOGOS!$B$19:$B$30,MATCH($E16,CATALOGOS!$A$19:$A$30,0)),0))} -> 0 | S16: {=IF($K16="",0,IFERROR(INDEX(CATALOGOS!$B$35:$B$42,MATCH($K16,CATALOGOS!$A$35:$A$42,0)),0))} -> 0 | T16: {=IF($J16="",0,IFERROR(INDEX(CATALOGOS!$B$47:$B$51,MATCH($J16,CATALOGOS!$A$47:$A$51,0)),0))} -> 0 | U16: {=IF($M16="",0,IFERROR(INDEX(CATALOGOS!$B$56:$B$62,MATCH($M16,CATALOGOS!$A$56:$A$62,0)),0))} -> 0 | V16: =IF($B16="","",IF($O16="Venta",SUM($Q16:$U16),0)) -> 45 | W16: {=IF($D16="",0,IFERROR(INDEX(CATALOGOS!$C$6:$C$14,MATCH($D16,CATALOGOS!$A$6:$A$14,0)),0))} -> 1 | X16: {=IF($D16="",0,IFERROR(INDEX(CATALOGOS!$D$6:$D$14,MATCH($D16,CATALOGOS!$A$6:$A$14,0)),0))} -> 1 | Y16: {=IF($D16="",0,IFERROR(INDEX(CATALOGOS!$E$6:$E$14,MATCH($D16,CATALOGOS!$A$6:$A$14,0)),0))} -> 1 | Z16: =IF(COUNTA($B16:$P16)=0,"",IF($B16="","nombre. ","")&IF($D16="","producto. ","")&IF($E16="","talla. ","")&IF($F16="","número. ","")&IF($H16="","género. ","")&IF($I16="","corte. ","")&IF($O16="","tipo. ",""))
A17: =IF($B17="","",ROW()-2) -> 15 | B17: CLINT | D17: Kit completo | E17: XL | F17: 69 | G17: Blanco hueso | H17: Hombre | I17: Recto | J17: Redondo | K17: Win Fresh | L17: Sí | M17: Sublimado | N17: No | O17: Venta | P17: Nombres de los hijos en las mangas; nombre de la esposa en el cuello delantero | Q17: {=IF($D17="","",IFERROR(INDEX(CATALOGOS!$B$6:$B$14,MATCH($D17,CATALOGOS!$A$6:$A$14,0)),0))} -> 45 | R17: {=IF($E17="",0,IFERROR(INDEX(CATALOGOS!$B$19:$B$30,MATCH($E17,CATALOGOS!$A$19:$A$30,0)),0))} -> 3 | S17: {=IF($K17="",0,IFERROR(INDEX(CATALOGOS!$B$35:$B$42,MATCH($K17,CATALOGOS!$A$35:$A$42,0)),0))} -> 0 | T17: {=IF($J17="",0,IFERROR(INDEX(CATALOGOS!$B$47:$B$51,MATCH($J17,CATALOGOS!$A$47:$A$51,0)),0))} -> 0 | U17: {=IF($M17="",0,IFERROR(INDEX(CATALOGOS!$B$56:$B$62,MATCH($M17,CATALOGOS!$A$56:$A$62,0)),0))} -> 0 | V17: =IF($B17="","",IF($O17="Venta",SUM($Q17:$U17),0)) -> 48 | W17: {=IF($D17="",0,IFERROR(INDEX(CATALOGOS!$C$6:$C$14,MATCH($D17,CATALOGOS!$A$6:$A$14,0)),0))} -> 1 | X17: {=IF($D17="",0,IFERROR(INDEX(CATALOGOS!$D$6:$D$14,MATCH($D17,CATALOGOS!$A$6:$A$14,0)),0))} -> 1 | Y17: {=IF($D17="",0,IFERROR(INDEX(CATALOGOS!$E$6:$E$14,MATCH($D17,CATALOGOS!$A$6:$A$14,0)),0))} -> 1 | Z17: =IF(COUNTA($B17:$P17)=0,"",IF($B17="","nombre. ","")&IF($D17="","producto. ","")&IF($E17="","talla. ","")&IF($F17="","número. ","")&IF($H17="","género. ","")&IF($I17="","corte. ","")&IF($O17="","tipo. ",""))
A18: =IF($B18="","",ROW()-2) -> 16 | B18: HA.LI | D18: Kit completo | E18: XL | F18: 119 | G18: Blanco hueso | H18: Hombre | I18: Recto | J18: Redondo | K18: Win Fresh | L18: Sí | M18: Sublimado | N18: No | O18: Venta | Q18: {=IF($D18="","",IFERROR(INDEX(CATALOGOS!$B$6:$B$14,MATCH($D18,CATALOGOS!$A$6:$A$14,0)),0))} -> 45 | R18: {=IF($E18="",0,IFERROR(INDEX(CATALOGOS!$B$19:$B$30,MATCH($E18,CATALOGOS!$A$19:$A$30,0)),0))} -> 3 | S18: {=IF($K18="",0,IFERROR(INDEX(CATALOGOS!$B$35:$B$42,MATCH($K18,CATALOGOS!$A$35:$A$42,0)),0))} -> 0 | T18: {=IF($J18="",0,IFERROR(INDEX(CATALOGOS!$B$47:$B$51,MATCH($J18,CATALOGOS!$A$47:$A$51,0)),0))} -> 0 | U18: {=IF($M18="",0,IFERROR(INDEX(CATALOGOS!$B$56:$B$62,MATCH($M18,CATALOGOS!$A$56:$A$62,0)),0))} -> 0 | V18: =IF($B18="","",IF($O18="Venta",SUM($Q18:$U18),0)) -> 48 | W18: {=IF($D18="",0,IFERROR(INDEX(CATALOGOS!$C$6:$C$14,MATCH($D18,CATALOGOS!$A$6:$A$14,0)),0))} -> 1 | X18: {=IF($D18="",0,IFERROR(INDEX(CATALOGOS!$D$6:$D$14,MATCH($D18,CATALOGOS!$A$6:$A$14,0)),0))} -> 1 | Y18: {=IF($D18="",0,IFERROR(INDEX(CATALOGOS!$E$6:$E$14,MATCH($D18,CATALOGOS!$A$6:$A$14,0)),0))} -> 1 | Z18: =IF(COUNTA($B18:$P18)=0,"",IF($B18="","nombre. ","")&IF($D18="","producto. ","")&IF($E18="","talla. ","")&IF($F18="","número. ","")&IF($H18="","género. ","")&IF($I18="","corte. ","")&IF($O18="","tipo. ",""))
A19: =IF($B19="","",ROW()-2) -> 17 | B19: THEO | D19: Camiseta sola | E19: 10 | F19: 69 | G19: Blanco hueso | H19: Niño | I19: Recto | J19: Redondo | K19: Win Fresh | L19: Sí | M19: Sublimado | N19: No | O19: Venta | Q19: {=IF($D19="","",IFERROR(INDEX(CATALOGOS!$B$6:$B$14,MATCH($D19,CATALOGOS!$A$6:$A$14,0)),0))} -> 25 | R19: {=IF($E19="",0,IFERROR(INDEX(CATALOGOS!$B$19:$B$30,MATCH($E19,CATALOGOS!$A$19:$A$30,0)),0))} -> 0 | S19: {=IF($K19="",0,IFERROR(INDEX(CATALOGOS!$B$35:$B$42,MATCH($K19,CATALOGOS!$A$35:$A$42,0)),0))} -> 0 | T19: {=IF($J19="",0,IFERROR(INDEX(CATALOGOS!$B$47:$B$51,MATCH($J19,CATALOGOS!$A$47:$A$51,0)),0))} -> 0 | U19: {=IF($M19="",0,IFERROR(INDEX(CATALOGOS!$B$56:$B$62,MATCH($M19,CATALOGOS!$A$56:$A$62,0)),0))} -> 0 | V19: =IF($B19="","",IF($O19="Venta",SUM($Q19:$U19),0)) -> 25 | W19: {=IF($D19="",0,IFERROR(INDEX(CATALOGOS!$C$6:$C$14,MATCH($D19,CATALOGOS!$A$6:$A$14,0)),0))} -> 1 | X19: {=IF($D19="",0,IFERROR(INDEX(CATALOGOS!$D$6:$D$14,MATCH($D19,CATALOGOS!$A$6:$A$14,0)),0))} -> 0 | Y19: {=IF($D19="",0,IFERROR(INDEX(CATALOGOS!$E$6:$E$14,MATCH($D19,CATALOGOS!$A$6:$A$14,0)),0))} -> 0 | Z19: =IF(COUNTA($B19:$P19)=0,"",IF($B19="","nombre. ","")&IF($D19="","producto. ","")&IF($E19="","talla. ","")&IF($F19="","número. ","")&IF($H19="","género. ","")&IF($I19="","corte. ","")&IF($O19="","tipo. ",""))
A20: =IF($B20="","",ROW()-2) -> 18 | B20: THIAGO R. | D20: Camiseta sola | E20: 14 | F20: 8 | G20: Blanco hueso | H20: Niño | I20: Recto | J20: Redondo | K20: Win Fresh | L20: Sí | M20: Sublimado | N20: No | O20: Venta | Q20: {=IF($D20="","",IFERROR(INDEX(CATALOGOS!$B$6:$B$14,MATCH($D20,CATALOGOS!$A$6:$A$14,0)),0))} -> 25 | R20: {=IF($E20="",0,IFERROR(INDEX(CATALOGOS!$B$19:$B$30,MATCH($E20,CATALOGOS!$A$19:$A$30,0)),0))} -> 0 | S20: {=IF($K20="",0,IFERROR(INDEX(CATALOGOS!$B$35:$B$42,MATCH($K20,CATALOGOS!$A$35:$A$42,0)),0))} -> 0 | T20: {=IF($J20="",0,IFERROR(INDEX(CATALOGOS!$B$47:$B$51,MATCH($J20,CATALOGOS!$A$47:$A$51,0)),0))} -> 0 | U20: {=IF($M20="",0,IFERROR(INDEX(CATALOGOS!$B$56:$B$62,MATCH($M20,CATALOGOS!$A$56:$A$62,0)),0))} -> 0 | V20: =IF($B20="","",IF($O20="Venta",SUM($Q20:$U20),0)) -> 25 | W20: {=IF($D20="",0,IFERROR(INDEX(CATALOGOS!$C$6:$C$14,MATCH($D20,CATALOGOS!$A$6:$A$14,0)),0))} -> 1 | X20: {=IF($D20="",0,IFERROR(INDEX(CATALOGOS!$D$6:$D$14,MATCH($D20,CATALOGOS!$A$6:$A$14,0)),0))} -> 0 | Y20: {=IF($D20="",0,IFERROR(INDEX(CATALOGOS!$E$6:$E$14,MATCH($D20,CATALOGOS!$A$6:$A$14,0)),0))} -> 0 | Z20: =IF(COUNTA($B20:$P20)=0,"",IF($B20="","nombre. ","")&IF($D20="","producto. ","")&IF($E20="","talla. ","")&IF($F20="","número. ","")&IF($H20="","género. ","")&IF($I20="","corte. ","")&IF($O20="","tipo. ",""))
A21: =IF($B21="","",ROW()-2) -> 19 | B21: AMPARO | D21: Camiseta sola | E21: S | F21: 4 | G21: Blanco hueso | H21: Mujer | I21: Entallado | J21: Redondo | K21: Win Fresh | L21: Sí | M21: Sublimado | N21: No | O21: Venta | Q21: {=IF($D21="","",IFERROR(INDEX(CATALOGOS!$B$6:$B$14,MATCH($D21,CATALOGOS!$A$6:$A$14,0)),0))} -> 25 | R21: {=IF($E21="",0,IFERROR(INDEX(CATALOGOS!$B$19:$B$30,MATCH($E21,CATALOGOS!$A$19:$A$30,0)),0))} -> 0 | S21: {=IF($K21="",0,IFERROR(INDEX(CATALOGOS!$B$35:$B$42,MATCH($K21,CATALOGOS!$A$35:$A$42,0)),0))} -> 0 | T21: {=IF($J21="",0,IFERROR(INDEX(CATALOGOS!$B$47:$B$51,MATCH($J21,CATALOGOS!$A$47:$A$51,0)),0))} -> 0 | U21: {=IF($M21="",0,IFERROR(INDEX(CATALOGOS!$B$56:$B$62,MATCH($M21,CATALOGOS!$A$56:$A$62,0)),0))} -> 0 | V21: =IF($B21="","",IF($O21="Venta",SUM($Q21:$U21),0)) -> 25 | W21: {=IF($D21="",0,IFERROR(INDEX(CATALOGOS!$C$6:$C$14,MATCH($D21,CATALOGOS!$A$6:$A$14,0)),0))} -> 1 | X21: {=IF($D21="",0,IFERROR(INDEX(CATALOGOS!$D$6:$D$14,MATCH($D21,CATALOGOS!$A$6:$A$14,0)),0))} -> 0 | Y21: {=IF($D21="",0,IFERROR(INDEX(CATALOGOS!$E$6:$E$14,MATCH($D21,CATALOGOS!$A$6:$A$14,0)),0))} -> 0 | Z21: =IF(COUNTA($B21:$P21)=0,"",IF($B21="","nombre. ","")&IF($D21="","producto. ","")&IF($E21="","talla. ","")&IF($F21="","número. ","")&IF($H21="","género. ","")&IF($I21="","corte. ","")&IF($O21="","tipo. ",""))
A22: =IF($B22="","",ROW()-2) -> 20 | B22: TOGUE | D22: Camiseta sola | E22: S | F22: 8 | G22: Blanco hueso | H22: Hombre | I22: Recto | J22: Redondo | K22: Win Fresh | L22: Sí | M22: Sublimado | N22: No | O22: Venta | Q22: {=IF($D22="","",IFERROR(INDEX(CATALOGOS!$B$6:$B$14,MATCH($D22,CATALOGOS!$A$6:$A$14,0)),0))} -> 25 | R22: {=IF($E22="",0,IFERROR(INDEX(CATALOGOS!$B$19:$B$30,MATCH($E22,CATALOGOS!$A$19:$A$30,0)),0))} -> 0 | S22: {=IF($K22="",0,IFERROR(INDEX(CATALOGOS!$B$35:$B$42,MATCH($K22,CATALOGOS!$A$35:$A$42,0)),0))} -> 0 | T22: {=IF($J22="",0,IFERROR(INDEX(CATALOGOS!$B$47:$B$51,MATCH($J22,CATALOGOS!$A$47:$A$51,0)),0))} -> 0 | U22: {=IF($M22="",0,IFERROR(INDEX(CATALOGOS!$B$56:$B$62,MATCH($M22,CATALOGOS!$A$56:$A$62,0)),0))} -> 0 | V22: =IF($B22="","",IF($O22="Venta",SUM($Q22:$U22),0)) -> 25 | W22: {=IF($D22="",0,IFERROR(INDEX(CATALOGOS!$C$6:$C$14,MATCH($D22,CATALOGOS!$A$6:$A$14,0)),0))} -> 1 | X22: {=IF($D22="",0,IFERROR(INDEX(CATALOGOS!$D$6:$D$14,MATCH($D22,CATALOGOS!$A$6:$A$14,0)),0))} -> 0 | Y22: {=IF($D22="",0,IFERROR(INDEX(CATALOGOS!$E$6:$E$14,MATCH($D22,CATALOGOS!$A$6:$A$14,0)),0))} -> 0 | Z22: =IF(COUNTA($B22:$P22)=0,"",IF($B22="","nombre. ","")&IF($D22="","producto. ","")&IF($E22="","talla. ","")&IF($F22="","número. ","")&IF($H22="","género. ","")&IF($I22="","corte. ","")&IF($O22="","tipo. ",""))
A23: =IF($B23="","",ROW()-2) -> 21 | B23: MIRTHA | D23: Camiseta sola | E23: S | F23: 23 | G23: Blanco hueso | H23: Mujer | I23: Entallado | J23: Redondo | K23: Win Fresh | L23: Sí | M23: Sublimado | N23: No | O23: Venta | Q23: {=IF($D23="","",IFERROR(INDEX(CATALOGOS!$B$6:$B$14,MATCH($D23,CATALOGOS!$A$6:$A$14,0)),0))} -> 25 | R23: {=IF($E23="",0,IFERROR(INDEX(CATALOGOS!$B$19:$B$30,MATCH($E23,CATALOGOS!$A$19:$A$30,0)),0))} -> 0 | S23: {=IF($K23="",0,IFERROR(INDEX(CATALOGOS!$B$35:$B$42,MATCH($K23,CATALOGOS!$A$35:$A$42,0)),0))} -> 0 | T23: {=IF($J23="",0,IFERROR(INDEX(CATALOGOS!$B$47:$B$51,MATCH($J23,CATALOGOS!$A$47:$A$51,0)),0))} -> 0 | U23: {=IF($M23="",0,IFERROR(INDEX(CATALOGOS!$B$56:$B$62,MATCH($M23,CATALOGOS!$A$56:$A$62,0)),0))} -> 0 | V23: =IF($B23="","",IF($O23="Venta",SUM($Q23:$U23),0)) -> 25 | W23: {=IF($D23="",0,IFERROR(INDEX(CATALOGOS!$C$6:$C$14,MATCH($D23,CATALOGOS!$A$6:$A$14,0)),0))} -> 1 | X23: {=IF($D23="",0,IFERROR(INDEX(CATALOGOS!$D$6:$D$14,MATCH($D23,CATALOGOS!$A$6:$A$14,0)),0))} -> 0 | Y23: {=IF($D23="",0,IFERROR(INDEX(CATALOGOS!$E$6:$E$14,MATCH($D23,CATALOGOS!$A$6:$A$14,0)),0))} -> 0 | Z23: =IF(COUNTA($B23:$P23)=0,"",IF($B23="","nombre. ","")&IF($D23="","producto. ","")&IF($E23="","talla. ","")&IF($F23="","número. ","")&IF($H23="","género. ","")&IF($I23="","corte. ","")&IF($O23="","tipo. ",""))
A24: =IF($B24="","",ROW()-2) -> 22 | B24: ANA LI | D24: Camiseta sola | E24: M | F24: 11 | G24: Blanco hueso | H24: Mujer | I24: Entallado | J24: Redondo | K24: Win Fresh | L24: Sí | M24: Sublimado | N24: No | O24: Venta | Q24: {=IF($D24="","",IFERROR(INDEX(CATALOGOS!$B$6:$B$14,MATCH($D24,CATALOGOS!$A$6:$A$14,0)),0))} -> 25 | R24: {=IF($E24="",0,IFERROR(INDEX(CATALOGOS!$B$19:$B$30,MATCH($E24,CATALOGOS!$A$19:$A$30,0)),0))} -> 0 | S24: {=IF($K24="",0,IFERROR(INDEX(CATALOGOS!$B$35:$B$42,MATCH($K24,CATALOGOS!$A$35:$A$42,0)),0))} -> 0 | T24: {=IF($J24="",0,IFERROR(INDEX(CATALOGOS!$B$47:$B$51,MATCH($J24,CATALOGOS!$A$47:$A$51,0)),0))} -> 0 | U24: {=IF($M24="",0,IFERROR(INDEX(CATALOGOS!$B$56:$B$62,MATCH($M24,CATALOGOS!$A$56:$A$62,0)),0))} -> 0 | V24: =IF($B24="","",IF($O24="Venta",SUM($Q24:$U24),0)) -> 25 | W24: {=IF($D24="",0,IFERROR(INDEX(CATALOGOS!$C$6:$C$14,MATCH($D24,CATALOGOS!$A$6:$A$14,0)),0))} -> 1 | X24: {=IF($D24="",0,IFERROR(INDEX(CATALOGOS!$D$6:$D$14,MATCH($D24,CATALOGOS!$A$6:$A$14,0)),0))} -> 0 | Y24: {=IF($D24="",0,IFERROR(INDEX(CATALOGOS!$E$6:$E$14,MATCH($D24,CATALOGOS!$A$6:$A$14,0)),0))} -> 0 | Z24: =IF(COUNTA($B24:$P24)=0,"",IF($B24="","nombre. ","")&IF($D24="","producto. ","")&IF($E24="","talla. ","")&IF($F24="","número. ","")&IF($H24="","género. ","")&IF($I24="","corte. ","")&IF($O24="","tipo. ",""))
A25: =IF($B25="","",ROW()-2) -> 23 | B25: LOCONI | D25: Camiseta sola | E25: M | F25: 98 | G25: Blanco hueso | H25: Hombre | I25: Recto | J25: Redondo | K25: Win Fresh | L25: Sí | M25: Sublimado | N25: No | O25: Venta | Q25: {=IF($D25="","",IFERROR(INDEX(CATALOGOS!$B$6:$B$14,MATCH($D25,CATALOGOS!$A$6:$A$14,0)),0))} -> 25 | R25: {=IF($E25="",0,IFERROR(INDEX(CATALOGOS!$B$19:$B$30,MATCH($E25,CATALOGOS!$A$19:$A$30,0)),0))} -> 0 | S25: {=IF($K25="",0,IFERROR(INDEX(CATALOGOS!$B$35:$B$42,MATCH($K25,CATALOGOS!$A$35:$A$42,0)),0))} -> 0 | T25: {=IF($J25="",0,IFERROR(INDEX(CATALOGOS!$B$47:$B$51,MATCH($J25,CATALOGOS!$A$47:$A$51,0)),0))} -> 0 | U25: {=IF($M25="",0,IFERROR(INDEX(CATALOGOS!$B$56:$B$62,MATCH($M25,CATALOGOS!$A$56:$A$62,0)),0))} -> 0 | V25: =IF($B25="","",IF($O25="Venta",SUM($Q25:$U25),0)) -> 25 | W25: {=IF($D25="",0,IFERROR(INDEX(CATALOGOS!$C$6:$C$14,MATCH($D25,CATALOGOS!$A$6:$A$14,0)),0))} -> 1 | X25: {=IF($D25="",0,IFERROR(INDEX(CATALOGOS!$D$6:$D$14,MATCH($D25,CATALOGOS!$A$6:$A$14,0)),0))} -> 0 | Y25: {=IF($D25="",0,IFERROR(INDEX(CATALOGOS!$E$6:$E$14,MATCH($D25,CATALOGOS!$A$6:$A$14,0)),0))} -> 0 | Z25: =IF(COUNTA($B25:$P25)=0,"",IF($B25="","nombre. ","")&IF($D25="","producto. ","")&IF($E25="","talla. ","")&IF($F25="","número. ","")&IF($H25="","género. ","")&IF($I25="","corte. ","")&IF($O25="","tipo. ",""))
A26: =IF($B26="","",ROW()-2) -> 24 | B26: HADA | D26: Camiseta sola | E26: M | F26: 8 | G26: Blanco hueso | H26: Mujer | I26: Entallado | J26: Redondo | K26: Win Fresh | L26: Sí | M26: Sublimado | N26: No | O26: Venta | Q26: {=IF($D26="","",IFERROR(INDEX(CATALOGOS!$B$6:$B$14,MATCH($D26,CATALOGOS!$A$6:$A$14,0)),0))} -> 25 | R26: {=IF($E26="",0,IFERROR(INDEX(CATALOGOS!$B$19:$B$30,MATCH($E26,CATALOGOS!$A$19:$A$30,0)),0))} -> 0 | S26: {=IF($K26="",0,IFERROR(INDEX(CATALOGOS!$B$35:$B$42,MATCH($K26,CATALOGOS!$A$35:$A$42,0)),0))} -> 0 | T26: {=IF($J26="",0,IFERROR(INDEX(CATALOGOS!$B$47:$B$51,MATCH($J26,CATALOGOS!$A$47:$A$51,0)),0))} -> 0 | U26: {=IF($M26="",0,IFERROR(INDEX(CATALOGOS!$B$56:$B$62,MATCH($M26,CATALOGOS!$A$56:$A$62,0)),0))} -> 0 | V26: =IF($B26="","",IF($O26="Venta",SUM($Q26:$U26),0)) -> 25 | W26: {=IF($D26="",0,IFERROR(INDEX(CATALOGOS!$C$6:$C$14,MATCH($D26,CATALOGOS!$A$6:$A$14,0)),0))} -> 1 | X26: {=IF($D26="",0,IFERROR(INDEX(CATALOGOS!$D$6:$D$14,MATCH($D26,CATALOGOS!$A$6:$A$14,0)),0))} -> 0 | Y26: {=IF($D26="",0,IFERROR(INDEX(CATALOGOS!$E$6:$E$14,MATCH($D26,CATALOGOS!$A$6:$A$14,0)),0))} -> 0 | Z26: =IF(COUNTA($B26:$P26)=0,"",IF($B26="","nombre. ","")&IF($D26="","producto. ","")&IF($E26="","talla. ","")&IF($F26="","número. ","")&IF($H26="","género. ","")&IF($I26="","corte. ","")&IF($O26="","tipo. ",""))
A27: =IF($B27="","",ROW()-2) -> 25 | B27: PATRICIA A. | D27: Camiseta sola | E27: M | F27: 10 | G27: Blanco hueso | H27: Mujer | I27: Entallado | J27: Redondo | K27: Win Fresh | L27: Sí | M27: Sublimado | N27: No | O27: Venta | Q27: {=IF($D27="","",IFERROR(INDEX(CATALOGOS!$B$6:$B$14,MATCH($D27,CATALOGOS!$A$6:$A$14,0)),0))} -> 25 | R27: {=IF($E27="",0,IFERROR(INDEX(CATALOGOS!$B$19:$B$30,MATCH($E27,CATALOGOS!$A$19:$A$30,0)),0))} -> 0 | S27: {=IF($K27="",0,IFERROR(INDEX(CATALOGOS!$B$35:$B$42,MATCH($K27,CATALOGOS!$A$35:$A$42,0)),0))} -> 0 | T27: {=IF($J27="",0,IFERROR(INDEX(CATALOGOS!$B$47:$B$51,MATCH($J27,CATALOGOS!$A$47:$A$51,0)),0))} -> 0 | U27: {=IF($M27="",0,IFERROR(INDEX(CATALOGOS!$B$56:$B$62,MATCH($M27,CATALOGOS!$A$56:$A$62,0)),0))} -> 0 | V27: =IF($B27="","",IF($O27="Venta",SUM($Q27:$U27),0)) -> 25 | W27: {=IF($D27="",0,IFERROR(INDEX(CATALOGOS!$C$6:$C$14,MATCH($D27,CATALOGOS!$A$6:$A$14,0)),0))} -> 1 | X27: {=IF($D27="",0,IFERROR(INDEX(CATALOGOS!$D$6:$D$14,MATCH($D27,CATALOGOS!$A$6:$A$14,0)),0))} -> 0 | Y27: {=IF($D27="",0,IFERROR(INDEX(CATALOGOS!$E$6:$E$14,MATCH($D27,CATALOGOS!$A$6:$A$14,0)),0))} -> 0 | Z27: =IF(COUNTA($B27:$P27)=0,"",IF($B27="","nombre. ","")&IF($D27="","producto. ","")&IF($E27="","talla. ","")&IF($F27="","número. ","")&IF($H27="","género. ","")&IF($I27="","corte. ","")&IF($O27="","tipo. ",""))
A28: =IF($B28="","",ROW()-2) -> 26 | B28: CYNTHIA | D28: Camiseta sola | E28: L | F28: 25 | G28: Blanco hueso | H28: Mujer | I28: Entallado | J28: Redondo | K28: Win Fresh | L28: Sí | M28: Sublimado | N28: No | O28: Venta | Q28: {=IF($D28="","",IFERROR(INDEX(CATALOGOS!$B$6:$B$14,MATCH($D28,CATALOGOS!$A$6:$A$14,0)),0))} -> 25 | R28: {=IF($E28="",0,IFERROR(INDEX(CATALOGOS!$B$19:$B$30,MATCH($E28,CATALOGOS!$A$19:$A$30,0)),0))} -> 0 | S28: {=IF($K28="",0,IFERROR(INDEX(CATALOGOS!$B$35:$B$42,MATCH($K28,CATALOGOS!$A$35:$A$42,0)),0))} -> 0 | T28: {=IF($J28="",0,IFERROR(INDEX(CATALOGOS!$B$47:$B$51,MATCH($J28,CATALOGOS!$A$47:$A$51,0)),0))} -> 0 | U28: {=IF($M28="",0,IFERROR(INDEX(CATALOGOS!$B$56:$B$62,MATCH($M28,CATALOGOS!$A$56:$A$62,0)),0))} -> 0 | V28: =IF($B28="","",IF($O28="Venta",SUM($Q28:$U28),0)) -> 25 | W28: {=IF($D28="",0,IFERROR(INDEX(CATALOGOS!$C$6:$C$14,MATCH($D28,CATALOGOS!$A$6:$A$14,0)),0))} -> 1 | X28: {=IF($D28="",0,IFERROR(INDEX(CATALOGOS!$D$6:$D$14,MATCH($D28,CATALOGOS!$A$6:$A$14,0)),0))} -> 0 | Y28: {=IF($D28="",0,IFERROR(INDEX(CATALOGOS!$E$6:$E$14,MATCH($D28,CATALOGOS!$A$6:$A$14,0)),0))} -> 0 | Z28: =IF(COUNTA($B28:$P28)=0,"",IF($B28="","nombre. ","")&IF($D28="","producto. ","")&IF($E28="","talla. ","")&IF($F28="","número. ","")&IF($H28="","género. ","")&IF($I28="","corte. ","")&IF($O28="","tipo. ",""))
A29: =IF($B29="","",ROW()-2) -> 27 | B29: TAPIA | D29: Kit completo | E29: L | F29: 23 | G29: Azul | H29: Hombre | I29: Recto | J29: Redondo | K29: Win Fresh | L29: Sí | M29: Sublimado | N29: No | O29: Venta | Q29: {=IF($D29="","",IFERROR(INDEX(CATALOGOS!$B$6:$B$14,MATCH($D29,CATALOGOS!$A$6:$A$14,0)),0))} -> 45 | R29: {=IF($E29="",0,IFERROR(INDEX(CATALOGOS!$B$19:$B$30,MATCH($E29,CATALOGOS!$A$19:$A$30,0)),0))} -> 0 | S29: {=IF($K29="",0,IFERROR(INDEX(CATALOGOS!$B$35:$B$42,MATCH($K29,CATALOGOS!$A$35:$A$42,0)),0))} -> 0 | T29: {=IF($J29="",0,IFERROR(INDEX(CATALOGOS!$B$47:$B$51,MATCH($J29,CATALOGOS!$A$47:$A$51,0)),0))} -> 0 | U29: {=IF($M29="",0,IFERROR(INDEX(CATALOGOS!$B$56:$B$62,MATCH($M29,CATALOGOS!$A$56:$A$62,0)),0))} -> 0 | V29: =IF($B29="","",IF($O29="Venta",SUM($Q29:$U29),0)) -> 45 | W29: {=IF($D29="",0,IFERROR(INDEX(CATALOGOS!$C$6:$C$14,MATCH($D29,CATALOGOS!$A$6:$A$14,0)),0))} -> 1 | X29: {=IF($D29="",0,IFERROR(INDEX(CATALOGOS!$D$6:$D$14,MATCH($D29,CATALOGOS!$A$6:$A$14,0)),0))} -> 1 | Y29: {=IF($D29="",0,IFERROR(INDEX(CATALOGOS!$E$6:$E$14,MATCH($D29,CATALOGOS!$A$6:$A$14,0)),0))} -> 1 | Z29: =IF(COUNTA($B29:$P29)=0,"",IF($B29="","nombre. ","")&IF($D29="","producto. ","")&IF($E29="","talla. ","")&IF($F29="","número. ","")&IF($H29="","género. ","")&IF($I29="","corte. ","")&IF($O29="","tipo. ",""))
A30: =IF($B30="","",ROW()-2) -> 28 | B30: CLINT | D30: Camiseta sola | E30: XL | F30: 69 | G30: Azul | H30: Hombre | I30: Recto | J30: Redondo | K30: Win Fresh | L30: Sí | M30: Sublimado | N30: No | O30: Venta | P30: Nombres de los hijos en las mangas; nombre de la esposa en el cuello delantero | Q30: {=IF($D30="","",IFERROR(INDEX(CATALOGOS!$B$6:$B$14,MATCH($D30,CATALOGOS!$A$6:$A$14,0)),0))} -> 25 | R30: {=IF($E30="",0,IFERROR(INDEX(CATALOGOS!$B$19:$B$30,MATCH($E30,CATALOGOS!$A$19:$A$30,0)),0))} -> 3 | S30: {=IF($K30="",0,IFERROR(INDEX(CATALOGOS!$B$35:$B$42,MATCH($K30,CATALOGOS!$A$35:$A$42,0)),0))} -> 0 | T30: {=IF($J30="",0,IFERROR(INDEX(CATALOGOS!$B$47:$B$51,MATCH($J30,CATALOGOS!$A$47:$A$51,0)),0))} -> 0 | U30: {=IF($M30="",0,IFERROR(INDEX(CATALOGOS!$B$56:$B$62,MATCH($M30,CATALOGOS!$A$56:$A$62,0)),0))} -> 0 | V30: =IF($B30="","",IF($O30="Venta",SUM($Q30:$U30),0)) -> 28 | W30: {=IF($D30="",0,IFERROR(INDEX(CATALOGOS!$C$6:$C$14,MATCH($D30,CATALOGOS!$A$6:$A$14,0)),0))} -> 1 | X30: {=IF($D30="",0,IFERROR(INDEX(CATALOGOS!$D$6:$D$14,MATCH($D30,CATALOGOS!$A$6:$A$14,0)),0))} -> 0 | Y30: {=IF($D30="",0,IFERROR(INDEX(CATALOGOS!$E$6:$E$14,MATCH($D30,CATALOGOS!$A$6:$A$14,0)),0))} -> 0 | Z30: =IF(COUNTA($B30:$P30)=0,"",IF($B30="","nombre. ","")&IF($D30="","producto. ","")&IF($E30="","talla. ","")&IF($F30="","número. ","")&IF($H30="","género. ","")&IF($I30="","corte. ","")&IF($O30="","tipo. ",""))
A31: =IF($B31="","",ROW()-2) | Q31: {=IF($D31="","",IFERROR(INDEX(CATALOGOS!$B$6:$B$14,MATCH($D31,CATALOGOS!$A$6:$A$14,0)),0))} | R31: {=IF($E31="",0,IFERROR(INDEX(CATALOGOS!$B$19:$B$30,MATCH($E31,CATALOGOS!$A$19:$A$30,0)),0))} -> 0 | S31: {=IF($K31="",0,IFERROR(INDEX(CATALOGOS!$B$35:$B$42,MATCH($K31,CATALOGOS!$A$35:$A$42,0)),0))} -> 0 | T31: {=IF($J31="",0,IFERROR(INDEX(CATALOGOS!$B$47:$B$51,MATCH($J31,CATALOGOS!$A$47:$A$51,0)),0))} -> 0 | U31: {=IF($M31="",0,IFERROR(INDEX(CATALOGOS!$B$56:$B$62,MATCH($M31,CATALOGOS!$A$56:$A$62,0)),0))} -> 0 | V31: =IF($B31="","",IF($O31="Venta",SUM($Q31:$U31),0)) | W31: {=IF($D31="",0,IFERROR(INDEX(CATALOGOS!$C$6:$C$14,MATCH($D31,CATALOGOS!$A$6:$A$14,0)),0))} -> 0 | X31: {=IF($D31="",0,IFERROR(INDEX(CATALOGOS!$D$6:$D$14,MATCH($D31,CATALOGOS!$A$6:$A$14,0)),0))} -> 0 | Y31: {=IF($D31="",0,IFERROR(INDEX(CATALOGOS!$E$6:$E$14,MATCH($D31,CATALOGOS!$A$6:$A$14,0)),0))} -> 0 | Z31: =IF(COUNTA($B31:$P31)=0,"",IF($B31="","nombre. ","")&IF($D31="","producto. ","")&IF($E31="","talla. ","")&IF($F31="","número. ","")&IF($H31="","género. ","")&IF($I31="","corte. ","")&IF($O31="","tipo. ",""))
A32: =IF($B32="","",ROW()-2) | Q32: {=IF($D32="","",IFERROR(INDEX(CATALOGOS!$B$6:$B$14,MATCH($D32,CATALOGOS!$A$6:$A$14,0)),0))} | R32: {=IF($E32="",0,IFERROR(INDEX(CATALOGOS!$B$19:$B$30,MATCH($E32,CATALOGOS!$A$19:$A$30,0)),0))} -> 0 | S32: {=IF($K32="",0,IFERROR(INDEX(CATALOGOS!$B$35:$B$42,MATCH($K32,CATALOGOS!$A$35:$A$42,0)),0))} -> 0 | T32: {=IF($J32="",0,IFERROR(INDEX(CATALOGOS!$B$47:$B$51,MATCH($J32,CATALOGOS!$A$47:$A$51,0)),0))} -> 0 | U32: {=IF($M32="",0,IFERROR(INDEX(CATALOGOS!$B$56:$B$62,MATCH($M32,CATALOGOS!$A$56:$A$62,0)),0))} -> 0 | V32: =IF($B32="","",IF($O32="Venta",SUM($Q32:$U32),0)) | W32: {=IF($D32="",0,IFERROR(INDEX(CATALOGOS!$C$6:$C$14,MATCH($D32,CATALOGOS!$A$6:$A$14,0)),0))} -> 0 | X32: {=IF($D32="",0,IFERROR(INDEX(CATALOGOS!$D$6:$D$14,MATCH($D32,CATALOGOS!$A$6:$A$14,0)),0))} -> 0 | Y32: {=IF($D32="",0,IFERROR(INDEX(CATALOGOS!$E$6:$E$14,MATCH($D32,CATALOGOS!$A$6:$A$14,0)),0))} -> 0 | Z32: =IF(COUNTA($B32:$P32)=0,"",IF($B32="","nombre. ","")&IF($D32="","producto. ","")&IF($E32="","talla. ","")&IF($F32="","número. ","")&IF($H32="","género. ","")&IF($I32="","corte. ","")&IF($O32="","tipo. ",""))
A33: =IF($B33="","",ROW()-2) | Q33: {=IF($D33="","",IFERROR(INDEX(CATALOGOS!$B$6:$B$14,MATCH($D33,CATALOGOS!$A$6:$A$14,0)),0))} | R33: {=IF($E33="",0,IFERROR(INDEX(CATALOGOS!$B$19:$B$30,MATCH($E33,CATALOGOS!$A$19:$A$30,0)),0))} -> 0 | S33: {=IF($K33="",0,IFERROR(INDEX(CATALOGOS!$B$35:$B$42,MATCH($K33,CATALOGOS!$A$35:$A$42,0)),0))} -> 0 | T33: {=IF($J33="",0,IFERROR(INDEX(CATALOGOS!$B$47:$B$51,MATCH($J33,CATALOGOS!$A$47:$A$51,0)),0))} -> 0 | U33: {=IF($M33="",0,IFERROR(INDEX(CATALOGOS!$B$56:$B$62,MATCH($M33,CATALOGOS!$A$56:$A$62,0)),0))} -> 0 | V33: =IF($B33="","",IF($O33="Venta",SUM($Q33:$U33),0)) | W33: {=IF($D33="",0,IFERROR(INDEX(CATALOGOS!$C$6:$C$14,MATCH($D33,CATALOGOS!$A$6:$A$14,0)),0))} -> 0 | X33: {=IF($D33="",0,IFERROR(INDEX(CATALOGOS!$D$6:$D$14,MATCH($D33,CATALOGOS!$A$6:$A$14,0)),0))} -> 0 | Y33: {=IF($D33="",0,IFERROR(INDEX(CATALOGOS!$E$6:$E$14,MATCH($D33,CATALOGOS!$A$6:$A$14,0)),0))} -> 0 | Z33: =IF(COUNTA($B33:$P33)=0,"",IF($B33="","nombre. ","")&IF($D33="","producto. ","")&IF($E33="","talla. ","")&IF($F33="","número. ","")&IF($H33="","género. ","")&IF($I33="","corte. ","")&IF($O33="","tipo. ",""))
A34: =IF($B34="","",ROW()-2) | Q34: {=IF($D34="","",IFERROR(INDEX(CATALOGOS!$B$6:$B$14,MATCH($D34,CATALOGOS!$A$6:$A$14,0)),0))} | R34: {=IF($E34="",0,IFERROR(INDEX(CATALOGOS!$B$19:$B$30,MATCH($E34,CATALOGOS!$A$19:$A$30,0)),0))} -> 0 | S34: {=IF($K34="",0,IFERROR(INDEX(CATALOGOS!$B$35:$B$42,MATCH($K34,CATALOGOS!$A$35:$A$42,0)),0))} -> 0 | T34: {=IF($J34="",0,IFERROR(INDEX(CATALOGOS!$B$47:$B$51,MATCH($J34,CATALOGOS!$A$47:$A$51,0)),0))} -> 0 | U34: {=IF($M34="",0,IFERROR(INDEX(CATALOGOS!$B$56:$B$62,MATCH($M34,CATALOGOS!$A$56:$A$62,0)),0))} -> 0 | V34: =IF($B34="","",IF($O34="Venta",SUM($Q34:$U34),0)) | W34: {=IF($D34="",0,IFERROR(INDEX(CATALOGOS!$C$6:$C$14,MATCH($D34,CATALOGOS!$A$6:$A$14,0)),0))} -> 0 | X34: {=IF($D34="",0,IFERROR(INDEX(CATALOGOS!$D$6:$D$14,MATCH($D34,CATALOGOS!$A$6:$A$14,0)),0))} -> 0 | Y34: {=IF($D34="",0,IFERROR(INDEX(CATALOGOS!$E$6:$E$14,MATCH($D34,CATALOGOS!$A$6:$A$14,0)),0))} -> 0 | Z34: =IF(COUNTA($B34:$P34)=0,"",IF($B34="","nombre. ","")&IF($D34="","producto. ","")&IF($E34="","talla. ","")&IF($F34="","número. ","")&IF($H34="","género. ","")&IF($I34="","corte. ","")&IF($O34="","tipo. ",""))
A35: =IF($B35="","",ROW()-2) | Q35: {=IF($D35="","",IFERROR(INDEX(CATALOGOS!$B$6:$B$14,MATCH($D35,CATALOGOS!$A$6:$A$14,0)),0))} | R35: {=IF($E35="",0,IFERROR(INDEX(CATALOGOS!$B$19:$B$30,MATCH($E35,CATALOGOS!$A$19:$A$30,0)),0))} -> 0 | S35: {=IF($K35="",0,IFERROR(INDEX(CATALOGOS!$B$35:$B$42,MATCH($K35,CATALOGOS!$A$35:$A$42,0)),0))} -> 0 | T35: {=IF($J35="",0,IFERROR(INDEX(CATALOGOS!$B$47:$B$51,MATCH($J35,CATALOGOS!$A$47:$A$51,0)),0))} -> 0 | U35: {=IF($M35="",0,IFERROR(INDEX(CATALOGOS!$B$56:$B$62,MATCH($M35,CATALOGOS!$A$56:$A$62,0)),0))} -> 0 | V35: =IF($B35="","",IF($O35="Venta",SUM($Q35:$U35),0)) | W35: {=IF($D35="",0,IFERROR(INDEX(CATALOGOS!$C$6:$C$14,MATCH($D35,CATALOGOS!$A$6:$A$14,0)),0))} -> 0 | X35: {=IF($D35="",0,IFERROR(INDEX(CATALOGOS!$D$6:$D$14,MATCH($D35,CATALOGOS!$A$6:$A$14,0)),0))} -> 0 | Y35: {=IF($D35="",0,IFERROR(INDEX(CATALOGOS!$E$6:$E$14,MATCH($D35,CATALOGOS!$A$6:$A$14,0)),0))} -> 0 | Z35: =IF(COUNTA($B35:$P35)=0,"",IF($B35="","nombre. ","")&IF($D35="","producto. ","")&IF($E35="","talla. ","")&IF($F35="","número. ","")&IF($H35="","género. ","")&IF($I35="","corte. ","")&IF($O35="","tipo. ",""))
A36: =IF($B36="","",ROW()-2) | Q36: {=IF($D36="","",IFERROR(INDEX(CATALOGOS!$B$6:$B$14,MATCH($D36,CATALOGOS!$A$6:$A$14,0)),0))} | R36: {=IF($E36="",0,IFERROR(INDEX(CATALOGOS!$B$19:$B$30,MATCH($E36,CATALOGOS!$A$19:$A$30,0)),0))} -> 0 | S36: {=IF($K36="",0,IFERROR(INDEX(CATALOGOS!$B$35:$B$42,MATCH($K36,CATALOGOS!$A$35:$A$42,0)),0))} -> 0 | T36: {=IF($J36="",0,IFERROR(INDEX(CATALOGOS!$B$47:$B$51,MATCH($J36,CATALOGOS!$A$47:$A$51,0)),0))} -> 0 | U36: {=IF($M36="",0,IFERROR(INDEX(CATALOGOS!$B$56:$B$62,MATCH($M36,CATALOGOS!$A$56:$A$62,0)),0))} -> 0 | V36: =IF($B36="","",IF($O36="Venta",SUM($Q36:$U36),0)) | W36: {=IF($D36="",0,IFERROR(INDEX(CATALOGOS!$C$6:$C$14,MATCH($D36,CATALOGOS!$A$6:$A$14,0)),0))} -> 0 | X36: {=IF($D36="",0,IFERROR(INDEX(CATALOGOS!$D$6:$D$14,MATCH($D36,CATALOGOS!$A$6:$A$14,0)),0))} -> 0 | Y36: {=IF($D36="",0,IFERROR(INDEX(CATALOGOS!$E$6:$E$14,MATCH($D36,CATALOGOS!$A$6:$A$14,0)),0))} -> 0 | Z36: =IF(COUNTA($B36:$P36)=0,"",IF($B36="","nombre. ","")&IF($D36="","producto. ","")&IF($E36="","talla. ","")&IF($F36="","número. ","")&IF($H36="","género. ","")&IF($I36="","corte. ","")&IF($O36="","tipo. ",""))
A37: =IF($B37="","",ROW()-2) | Q37: {=IF($D37="","",IFERROR(INDEX(CATALOGOS!$B$6:$B$14,MATCH($D37,CATALOGOS!$A$6:$A$14,0)),0))} | R37: {=IF($E37="",0,IFERROR(INDEX(CATALOGOS!$B$19:$B$30,MATCH($E37,CATALOGOS!$A$19:$A$30,0)),0))} -> 0 | S37: {=IF($K37="",0,IFERROR(INDEX(CATALOGOS!$B$35:$B$42,MATCH($K37,CATALOGOS!$A$35:$A$42,0)),0))} -> 0 | T37: {=IF($J37="",0,IFERROR(INDEX(CATALOGOS!$B$47:$B$51,MATCH($J37,CATALOGOS!$A$47:$A$51,0)),0))} -> 0 | U37: {=IF($M37="",0,IFERROR(INDEX(CATALOGOS!$B$56:$B$62,MATCH($M37,CATALOGOS!$A$56:$A$62,0)),0))} -> 0 | V37: =IF($B37="","",IF($O37="Venta",SUM($Q37:$U37),0)) | W37: {=IF($D37="",0,IFERROR(INDEX(CATALOGOS!$C$6:$C$14,MATCH($D37,CATALOGOS!$A$6:$A$14,0)),0))} -> 0 | X37: {=IF($D37="",0,IFERROR(INDEX(CATALOGOS!$D$6:$D$14,MATCH($D37,CATALOGOS!$A$6:$A$14,0)),0))} -> 0 | Y37: {=IF($D37="",0,IFERROR(INDEX(CATALOGOS!$E$6:$E$14,MATCH($D37,CATALOGOS!$A$6:$A$14,0)),0))} -> 0 | Z37: =IF(COUNTA($B37:$P37)=0,"",IF($B37="","nombre. ","")&IF($D37="","producto. ","")&IF($E37="","talla. ","")&IF($F37="","número. ","")&IF($H37="","género. ","")&IF($I37="","corte. ","")&IF($O37="","tipo. ",""))
A38: =IF($B38="","",ROW()-2) | Q38: {=IF($D38="","",IFERROR(INDEX(CATALOGOS!$B$6:$B$14,MATCH($D38,CATALOGOS!$A$6:$A$14,0)),0))} | R38: {=IF($E38="",0,IFERROR(INDEX(CATALOGOS!$B$19:$B$30,MATCH($E38,CATALOGOS!$A$19:$A$30,0)),0))} -> 0 | S38: {=IF($K38="",0,IFERROR(INDEX(CATALOGOS!$B$35:$B$42,MATCH($K38,CATALOGOS!$A$35:$A$42,0)),0))} -> 0 | T38: {=IF($J38="",0,IFERROR(INDEX(CATALOGOS!$B$47:$B$51,MATCH($J38,CATALOGOS!$A$47:$A$51,0)),0))} -> 0 | U38: {=IF($M38="",0,IFERROR(INDEX(CATALOGOS!$B$56:$B$62,MATCH($M38,CATALOGOS!$A$56:$A$62,0)),0))} -> 0 | V38: =IF($B38="","",IF($O38="Venta",SUM($Q38:$U38),0)) | W38: {=IF($D38="",0,IFERROR(INDEX(CATALOGOS!$C$6:$C$14,MATCH($D38,CATALOGOS!$A$6:$A$14,0)),0))} -> 0 | X38: {=IF($D38="",0,IFERROR(INDEX(CATALOGOS!$D$6:$D$14,MATCH($D38,CATALOGOS!$A$6:$A$14,0)),0))} -> 0 | Y38: {=IF($D38="",0,IFERROR(INDEX(CATALOGOS!$E$6:$E$14,MATCH($D38,CATALOGOS!$A$6:$A$14,0)),0))} -> 0 | Z38: =IF(COUNTA($B38:$P38)=0,"",IF($B38="","nombre. ","")&IF($D38="","producto. ","")&IF($E38="","talla. ","")&IF($F38="","número. ","")&IF($H38="","género. ","")&IF($I38="","corte. ","")&IF($O38="","tipo. ",""))
A39: =IF($B39="","",ROW()-2) | Q39: {=IF($D39="","",IFERROR(INDEX(CATALOGOS!$B$6:$B$14,MATCH($D39,CATALOGOS!$A$6:$A$14,0)),0))} | R39: {=IF($E39="",0,IFERROR(INDEX(CATALOGOS!$B$19:$B$30,MATCH($E39,CATALOGOS!$A$19:$A$30,0)),0))} -> 0 | S39: {=IF($K39="",0,IFERROR(INDEX(CATALOGOS!$B$35:$B$42,MATCH($K39,CATALOGOS!$A$35:$A$42,0)),0))} -> 0 | T39: {=IF($J39="",0,IFERROR(INDEX(CATALOGOS!$B$47:$B$51,MATCH($J39,CATALOGOS!$A$47:$A$51,0)),0))} -> 0 | U39: {=IF($M39="",0,IFERROR(INDEX(CATALOGOS!$B$56:$B$62,MATCH($M39,CATALOGOS!$A$56:$A$62,0)),0))} -> 0 | V39: =IF($B39="","",IF($O39="Venta",SUM($Q39:$U39),0)) | W39: {=IF($D39="",0,IFERROR(INDEX(CATALOGOS!$C$6:$C$14,MATCH($D39,CATALOGOS!$A$6:$A$14,0)),0))} -> 0 | X39: {=IF($D39="",0,IFERROR(INDEX(CATALOGOS!$D$6:$D$14,MATCH($D39,CATALOGOS!$A$6:$A$14,0)),0))} -> 0 | Y39: {=IF($D39="",0,IFERROR(INDEX(CATALOGOS!$E$6:$E$14,MATCH($D39,CATALOGOS!$A$6:$A$14,0)),0))} -> 0 | Z39: =IF(COUNTA($B39:$P39)=0,"",IF($B39="","nombre. ","")&IF($D39="","producto. ","")&IF($E39="","talla. ","")&IF($F39="","número. ","")&IF($H39="","género. ","")&IF($I39="","corte. ","")&IF($O39="","tipo. ",""))
A40: =IF($B40="","",ROW()-2) | Q40: {=IF($D40="","",IFERROR(INDEX(CATALOGOS!$B$6:$B$14,MATCH($D40,CATALOGOS!$A$6:$A$14,0)),0))} | R40: {=IF($E40="",0,IFERROR(INDEX(CATALOGOS!$B$19:$B$30,MATCH($E40,CATALOGOS!$A$19:$A$30,0)),0))} -> 0 | S40: {=IF($K40="",0,IFERROR(INDEX(CATALOGOS!$B$35:$B$42,MATCH($K40,CATALOGOS!$A$35:$A$42,0)),0))} -> 0 | T40: {=IF($J40="",0,IFERROR(INDEX(CATALOGOS!$B$47:$B$51,MATCH($J40,CATALOGOS!$A$47:$A$51,0)),0))} -> 0 | U40: {=IF($M40="",0,IFERROR(INDEX(CATALOGOS!$B$56:$B$62,MATCH($M40,CATALOGOS!$A$56:$A$62,0)),0))} -> 0 | V40: =IF($B40="","",IF($O40="Venta",SUM($Q40:$U40),0)) | W40: {=IF($D40="",0,IFERROR(INDEX(CATALOGOS!$C$6:$C$14,MATCH($D40,CATALOGOS!$A$6:$A$14,0)),0))} -> 0 | X40: {=IF($D40="",0,IFERROR(INDEX(CATALOGOS!$D$6:$D$14,MATCH($D40,CATALOGOS!$A$6:$A$14,0)),0))} -> 0 | Y40: {=IF($D40="",0,IFERROR(INDEX(CATALOGOS!$E$6:$E$14,MATCH($D40,CATALOGOS!$A$6:$A$14,0)),0))} -> 0 | Z40: =IF(COUNTA($B40:$P40)=0,"",IF($B40="","nombre. ","")&IF($D40="","producto. ","")&IF($E40="","talla. ","")&IF($F40="","número. ","")&IF($H40="","género. ","")&IF($I40="","corte. ","")&IF($O40="","tipo. ",""))
A41: =IF($B41="","",ROW()-2) | Q41: {=IF($D41="","",IFERROR(INDEX(CATALOGOS!$B$6:$B$14,MATCH($D41,CATALOGOS!$A$6:$A$14,0)),0))} | R41: {=IF($E41="",0,IFERROR(INDEX(CATALOGOS!$B$19:$B$30,MATCH($E41,CATALOGOS!$A$19:$A$30,0)),0))} -> 0 | S41: {=IF($K41="",0,IFERROR(INDEX(CATALOGOS!$B$35:$B$42,MATCH($K41,CATALOGOS!$A$35:$A$42,0)),0))} -> 0 | T41: {=IF($J41="",0,IFERROR(INDEX(CATALOGOS!$B$47:$B$51,MATCH($J41,CATALOGOS!$A$47:$A$51,0)),0))} -> 0 | U41: {=IF($M41="",0,IFERROR(INDEX(CATALOGOS!$B$56:$B$62,MATCH($M41,CATALOGOS!$A$56:$A$62,0)),0))} -> 0 | V41: =IF($B41="","",IF($O41="Venta",SUM($Q41:$U41),0)) | W41: {=IF($D41="",0,IFERROR(INDEX(CATALOGOS!$C$6:$C$14,MATCH($D41,CATALOGOS!$A$6:$A$14,0)),0))} -> 0 | X41: {=IF($D41="",0,IFERROR(INDEX(CATALOGOS!$D$6:$D$14,MATCH($D41,CATALOGOS!$A$6:$A$14,0)),0))} -> 0 | Y41: {=IF($D41="",0,IFERROR(INDEX(CATALOGOS!$E$6:$E$14,MATCH($D41,CATALOGOS!$A$6:$A$14,0)),0))} -> 0 | Z41: =IF(COUNTA($B41:$P41)=0,"",IF($B41="","nombre. ","")&IF($D41="","producto. ","")&IF($E41="","talla. ","")&IF($F41="","número. ","")&IF($H41="","género. ","")&IF($I41="","corte. ","")&IF($O41="","tipo. ",""))
A42: =IF($B42="","",ROW()-2) | Q42: {=IF($D42="","",IFERROR(INDEX(CATALOGOS!$B$6:$B$14,MATCH($D42,CATALOGOS!$A$6:$A$14,0)),0))} | R42: {=IF($E42="",0,IFERROR(INDEX(CATALOGOS!$B$19:$B$30,MATCH($E42,CATALOGOS!$A$19:$A$30,0)),0))} -> 0 | S42: {=IF($K42="",0,IFERROR(INDEX(CATALOGOS!$B$35:$B$42,MATCH($K42,CATALOGOS!$A$35:$A$42,0)),0))} -> 0 | T42: {=IF($J42="",0,IFERROR(INDEX(CATALOGOS!$B$47:$B$51,MATCH($J42,CATALOGOS!$A$47:$A$51,0)),0))} -> 0 | U42: {=IF($M42="",0,IFERROR(INDEX(CATALOGOS!$B$56:$B$62,MATCH($M42,CATALOGOS!$A$56:$A$62,0)),0))} -> 0 | V42: =IF($B42="","",IF($O42="Venta",SUM($Q42:$U42),0)) | W42: {=IF($D42="",0,IFERROR(INDEX(CATALOGOS!$C$6:$C$14,MATCH($D42,CATALOGOS!$A$6:$A$14,0)),0))} -> 0 | X42: {=IF($D42="",0,IFERROR(INDEX(CATALOGOS!$D$6:$D$14,MATCH($D42,CATALOGOS!$A$6:$A$14,0)),0))} -> 0 | Y42: {=IF($D42="",0,IFERROR(INDEX(CATALOGOS!$E$6:$E$14,MATCH($D42,CATALOGOS!$A$6:$A$14,0)),0))} -> 0 | Z42: =IF(COUNTA($B42:$P42)=0,"",IF($B42="","nombre. ","")&IF($D42="","producto. ","")&IF($E42="","talla. ","")&IF($F42="","número. ","")&IF($H42="","género. ","")&IF($I42="","corte. ","")&IF($O42="","tipo. ",""))
... A202: =IF($B202="","",ROW()-2) | Q202: {=IF($D202="","",IFERROR(INDEX(CATALOGOS!$B$6:$B$14,MATCH($D202,CATALOGOS!$A$6:$A$14,0)),0))} | R202: {=IF($E202="",0,IFERROR(INDEX(CATALOGOS!$B$19:$B$30,MATCH($E202,CATALOGOS!$A$19:$A$30,0)),0))} -> 0 | S202: {=IF($K202="",0,IFERROR(INDEX(CATALOGOS!$B$35:$B$42,MATCH($K202,CATALOGOS!$A$35:$A$42,0)),0))} -> 0 | T202: {=IF($J202="",0,IFERROR(INDEX(CATALOGOS!$B$47:$B$51,MATCH($J202,CATALOGOS!$A$47:$A$51,0)),0))} -> 0 | U202: {=IF($M202="",0,IFERROR(INDEX(CATALOGOS!$B$56:$B$62,MATCH($M202,CATALOGOS!$A$56:$A$62,0)),0))} -> 0 | V202: =IF($B202="","",IF($O202="Venta",SUM($Q202:$U202),0)) | W202: {=IF($D202="",0,IFERROR(INDEX(CATALOGOS!$C$6:$C$14,MATCH($D202,CATALOGOS!$A$6:$A$14,0)),0))} -> 0 | X202: {=IF($D202="",0,IFERROR(INDEX(CATALOGOS!$D$6:$D$14,MATCH($D202,CATALOGOS!$A$6:$A$14,0)),0))} -> 0 | Y202: {=IF($D202="",0,IFERROR(INDEX(CATALOGOS!$E$6:$E$14,MATCH($D202,CATALOGOS!$A$6:$A$14,0)),0))} -> 0 | Z202: =IF(COUNTA($B202:$P202)=0,"",IF($B202="","nombre. ","")&IF($D202="","producto. ","")&IF($E202="","talla. ","")&IF($F202="","número. ","")&IF($H202="","género. ","")&IF($I202="","corte. ","")&IF($O202="","tipo. ",""))

Sheet PROFORMA
B2: [ LOGO SUBLITEX ] | D2: GRAN CARTEL S.A.C.
D3: RUC 20544457846 | G3: ◀ VERIFICAR RUC
D4: Av. Aramburú cuadra 7 — Surquillo, Lima
D5: WhatsApp 944 941 179
D6: Sublimación digital de prendas deportivas
B9: PROFORMA DE PEDIDO
B10: N° de pedido | C10: =IF(PEDIDO!$B$5="","—",PEDIDO!$B$5) -> SUB-000842 | E10: Fecha | F10: =IF(PEDIDO!$F$5="","—",PEDIDO!$F$5) -> 2026-08-07
B11: Cliente | C11: =IF(PEDIDO!$B$7="","—",PEDIDO!$B$7) -> PROMO 2002 | E11: RUC / DNI | F11: =IF(PEDIDO!$F$7="","—",PEDIDO!$F$7) -> —
B12: Coordinador | C12: =IF(PEDIDO!$B$8="","—",PEDIDO!$B$8) -> Coordinador de la promoción | E12: Teléfono | F12: =IF(PEDIDO!$F$8="","—",PEDIDO!$F$8) -> +51 966 826 524
B13: Vendedora | C13: =IF(PEDIDO!$B$9="","—",PEDIDO!$B$9) -> — | E13: Entrega | F13: =IF(PEDIDO!$F$9="","—",PEDIDO!$F$9) -> 2026-08-18
B15: DISEÑO APROBADO
B16: INSERTAR AQUÍ LA IMAGEN DEL MOCKUP (Insertar › Imagen, y ajustarla dentro de este recuadro)
B30: Versión del mockup | C30: =IF(PEDIDO!$B$13="","—",PEDIDO!$B$13) -> v4 | E30: Aprobado el | F30: =IF(PEDIDO!$F$13="","—",PEDIDO!$F$13) -> 2026-08-07
B32: DETALLE DE LA COTIZACIÓN
B33: Descripción | C33: Detalle | D33: Cantidad | E33: P. unit. | F33: Subtotal
B34: =IF(E34=0,"",CATALOGOS!$A$6) -> Camiseta sola | C34: =IF(E34=0,"","Sublimado — diseño aprobado") -> Sublimado — diseño aprobado | D34: =COUNTIFS(PRENDAS!$D$3:$D$202,CATALOGOS!$A$6,PRENDAS!$O$3:$O$202,"Venta") -> 11 | E34: =IF(D34=0,0,CATALOGOS!$B$6) -> 25 | F34: =IF(D34=0,"",SUMIFS(PRENDAS!$Q$3:$Q$202,PRENDAS!$D$3:$D$202,CATALOGOS!$A$6,PRENDAS!$O$3:$O$202,"Venta")) -> 275
B35: =IF(E35=0,"",CATALOGOS!$A$7) | C35: =IF(E35=0,"","Sublimado — diseño aprobado") | D35: =COUNTIFS(PRENDAS!$D$3:$D$202,CATALOGOS!$A$7,PRENDAS!$O$3:$O$202,"Venta") -> 0 | E35: =IF(D35=0,0,CATALOGOS!$B$7) -> 0 | F35: =IF(D35=0,"",SUMIFS(PRENDAS!$Q$3:$Q$202,PRENDAS!$D$3:$D$202,CATALOGOS!$A$7,PRENDAS!$O$3:$O$202,"Venta"))
B36: =IF(E36=0,"",CATALOGOS!$A$8) -> Kit completo | C36: =IF(E36=0,"","Sublimado — diseño aprobado") -> Sublimado — diseño aprobado | D36: =COUNTIFS(PRENDAS!$D$3:$D$202,CATALOGOS!$A$8,PRENDAS!$O$3:$O$202,"Venta") -> 17 | E36: =IF(D36=0,0,CATALOGOS!$B$8) -> 45 | F36: =IF(D36=0,"",SUMIFS(PRENDAS!$Q$3:$Q$202,PRENDAS!$D$3:$D$202,CATALOGOS!$A$8,PRENDAS!$O$3:$O$202,"Venta")) -> 765
B37: =IF(E37=0,"",CATALOGOS!$A$9) | C37: =IF(E37=0,"","Sublimado — diseño aprobado") | D37: =COUNTIFS(PRENDAS!$D$3:$D$202,CATALOGOS!$A$9,PRENDAS!$O$3:$O$202,"Venta") -> 0 | E37: =IF(D37=0,0,CATALOGOS!$B$9) -> 0 | F37: =IF(D37=0,"",SUMIFS(PRENDAS!$Q$3:$Q$202,PRENDAS!$D$3:$D$202,CATALOGOS!$A$9,PRENDAS!$O$3:$O$202,"Venta"))
B38: =IF(E38=0,"",CATALOGOS!$A$10) | C38: =IF(E38=0,"","Sublimado — diseño aprobado") | D38: =COUNTIFS(PRENDAS!$D$3:$D$202,CATALOGOS!$A$10,PRENDAS!$O$3:$O$202,"Venta") -> 0 | E38: =IF(D38=0,0,CATALOGOS!$B$10) -> 0 | F38: =IF(D38=0,"",SUMIFS(PRENDAS!$Q$3:$Q$202,PRENDAS!$D$3:$D$202,CATALOGOS!$A$10,PRENDAS!$O$3:$O$202,"Venta"))
B39: =IF(E39=0,"",CATALOGOS!$A$11) | C39: =IF(E39=0,"","Sublimado — diseño aprobado") | D39: =COUNTIFS(PRENDAS!$D$3:$D$202,CATALOGOS!$A$11,PRENDAS!$O$3:$O$202,"Venta") -> 0 | E39: =IF(D39=0,0,CATALOGOS!$B$11) -> 0 | F39: =IF(D39=0,"",SUMIFS(PRENDAS!$Q$3:$Q$202,PRENDAS!$D$3:$D$202,CATALOGOS!$A$11,PRENDAS!$O$3:$O$202,"Venta"))
B40: =IF(E40=0,"",CATALOGOS!$A$12) | C40: =IF(E40=0,"","Sublimado — diseño aprobado") | D40: =COUNTIFS(PRENDAS!$D$3:$D$202,CATALOGOS!$A$12,PRENDAS!$O$3:$O$202,"Venta") -> 0 | E40: =IF(D40=0,0,CATALOGOS!$B$12) -> 0 | F40: =IF(D40=0,"",SUMIFS(PRENDAS!$Q$3:$Q$202,PRENDAS!$D$3:$D$202,CATALOGOS!$A$12,PRENDAS!$O$3:$O$202,"Venta"))
B41: =IF(E41=0,"",CATALOGOS!$A$13) | C41: =IF(E41=0,"","Sublimado — diseño aprobado") | D41: =COUNTIFS(PRENDAS!$D$3:$D$202,CATALOGOS!$A$13,PRENDAS!$O$3:$O$202,"Venta") -> 0 | E41: =IF(D41=0,0,CATALOGOS!$B$13) -> 0 | F41: =IF(D41=0,"",SUMIFS(PRENDAS!$Q$3:$Q$202,PRENDAS!$D$3:$D$202,CATALOGOS!$A$13,PRENDAS!$O$3:$O$202,"Venta"))
B42: =IF(E42=0,"",CATALOGOS!$A$14) | C42: =IF(E42=0,"","Sublimado — diseño aprobado") | D42: =COUNTIFS(PRENDAS!$D$3:$D$202,CATALOGOS!$A$14,PRENDAS!$O$3:$O$202,"Venta") -> 0 | E42: =IF(D42=0,0,CATALOGOS!$B$14) -> 0 | F42: =IF(D42=0,"",SUMIFS(PRENDAS!$Q$3:$Q$202,PRENDAS!$D$3:$D$202,CATALOGOS!$A$14,PRENDAS!$O$3:$O$202,"Venta"))
B43: Recargo por tallas especiales | F43: =SUMIFS(PRENDAS!$R$3:$R$202,PRENDAS!$O$3:$O$202,"Venta") -> 9
B44: Recargo por tela | F44: =SUMIFS(PRENDAS!$S$3:$S$202,PRENDAS!$O$3:$O$202,"Venta") -> 0
B45: Recargo por cuello | F45: =SUMIFS(PRENDAS!$T$3:$T$202,PRENDAS!$O$3:$O$202,"Venta") -> 0
B46: Recargo por acabados | F46: =SUMIFS(PRENDAS!$U$3:$U$202,PRENDAS!$O$3:$O$202,"Venta") -> 0
B47: Prendas de obsequio o muestra (sin costo) | D47: =COUNTIFS(PRENDAS!$O$3:$O$202,"Obsequio")+COUNTIFS(PRENDAS!$O$3:$O$202,"Muestra") -> 0 | F47: 0
E49: TOTAL SIN IGV | F49: =SUM(F34:F46) -> 1049
E50: Los precios no incluyen IGV (18%)
B52: PAGOS
B53: Adelanto sugerido (50%) | F53: =ROUND(F49*CATALOGOS!$B$76,2) -> 524.5
B54: Adelanto recibido | F54: 0
B55: Saldo pendiente | F55: =F49-F54 -> 1049
B57: CONDICIONES
B58: • Los precios no incluyen IGV. El 18% se calcula solo si se solicita boleta o factura.
B59: • El plazo de producción es de 4 a 7 días hábiles y empieza cuando están el diseño aprobado, el adelanto confirmado y la información del pedido cerrada.
B60: • No se despacha ningún pedido con saldo pendiente.
B61: • Los colores se aproximan al código acordado; la tela y la iluminación pueden variar la percepción del tono.
B62: • Cualquier cambio después de aprobar el diseño requiere confirmación y puede modificar el plazo.
B64: DATOS PARA EL PAGO
B65: Plin / transferencia | C65: Wilber Peralta Flores — 944941179
B66: Scotiabank — cuenta | C66: GRAN CARTEL S.A.C. — 0448814517
B67: Scotiabank — CCI | C67: 00923020044881451748
B70: Conformidad del cliente:
B72: _________________________________
B73: Nombre, DNI y fecha

Sheet DETALLE
A1: DETALLE DEL PEDIDO — página 2 · el cliente revisa y confirma
A2: =CONCATENATE("Pedido ",PEDIDO!$B$5," · ",PEDIDO!$B$7," · versión ",PEDIDO!$B$6) -> Pedido SUB-000842 · PROMO 2002 · versión 4
A4: RESÚMENES CALCULADOS
A5: Por componente físico | C5: Camisetas | D5: =SUM(PRENDAS!$W$3:$W$202) -> 28 | E5: Shorts | F5: =SUM(PRENDAS!$X$3:$X$202) -> 17 | G5: Medias | H5: =SUM(PRENDAS!$Y$3:$Y$202) -> 17
A6: Total de prendas | C6: =COUNTA(PRENDAS!$B$3:$B$202) -> 28 | E6: De venta | F6: =COUNTIFS(PRENDAS!$O$3:$O$202,"Venta",PRENDAS!$B$3:$B$202,"<>") -> 28 | G6: Obsequio/muestra | H6: =COUNTIFS(PRENDAS!$O$3:$O$202,"Obsequio")+COUNTIFS(PRENDAS!$O$3:$O$202,"Muestra") -> 0
A8: POR TALLA | D8: POR CORTE | G8: POR GÉNERO
A9: =CATALOGOS!$A$19 -> 6 | B9: =COUNTIFS(PRENDAS!$E$3:$E$202,CATALOGOS!$A$19) -> 0 | D9: =CATALOGOS!$B$67 -> Recto | E9: =COUNTIFS(PRENDAS!$I$3:$I$202,CATALOGOS!$B$67) -> 22 | G9: =CATALOGOS!$A$67 -> Hombre | H9: =COUNTIFS(PRENDAS!$H$3:$H$202,CATALOGOS!$A$67) -> 20
A10: =CATALOGOS!$A$20 -> 8 | B10: =COUNTIFS(PRENDAS!$E$3:$E$202,CATALOGOS!$A$20) -> 0 | D10: =CATALOGOS!$B$68 -> Entallado | E10: =COUNTIFS(PRENDAS!$I$3:$I$202,CATALOGOS!$B$68) -> 6 | G10: =CATALOGOS!$A$68 -> Mujer | H10: =COUNTIFS(PRENDAS!$H$3:$H$202,CATALOGOS!$A$68) -> 6
A11: =CATALOGOS!$A$21 -> 10 | B11: =COUNTIFS(PRENDAS!$E$3:$E$202,CATALOGOS!$A$21) -> 1 | D11: =CATALOGOS!$B$69 -> Princesa | E11: =COUNTIFS(PRENDAS!$I$3:$I$202,CATALOGOS!$B$69) -> 0 | G11: =CATALOGOS!$A$69 -> Niño | H11: =COUNTIFS(PRENDAS!$H$3:$H$202,CATALOGOS!$A$69) -> 2
A12: =CATALOGOS!$A$22 -> 12 | B12: =COUNTIFS(PRENDAS!$E$3:$E$202,CATALOGOS!$A$22) -> 0 | G12: =CATALOGOS!$A$70 -> Niña | H12: =COUNTIFS(PRENDAS!$H$3:$H$202,CATALOGOS!$A$70) -> 0
A13: =CATALOGOS!$A$23 -> 14 | B13: =COUNTIFS(PRENDAS!$E$3:$E$202,CATALOGOS!$A$23) -> 1 | G13: =CATALOGOS!$A$71 -> Sin especificar | H13: =COUNTIFS(PRENDAS!$H$3:$H$202,CATALOGOS!$A$71) -> 0
A14: =CATALOGOS!$A$24 -> 16 | B14: =COUNTIFS(PRENDAS!$E$3:$E$202,CATALOGOS!$A$24) -> 0
A15: =CATALOGOS!$A$25 -> S | B15: =COUNTIFS(PRENDAS!$E$3:$E$202,CATALOGOS!$A$25) -> 3
A16: =CATALOGOS!$A$26 -> M | B16: =COUNTIFS(PRENDAS!$E$3:$E$202,CATALOGOS!$A$26) -> 12
A17: =CATALOGOS!$A$27 -> L | B17: =COUNTIFS(PRENDAS!$E$3:$E$202,CATALOGOS!$A$27) -> 8
A18: =CATALOGOS!$A$28 -> XL | B18: =COUNTIFS(PRENDAS!$E$3:$E$202,CATALOGOS!$A$28) -> 3
A19: =CATALOGOS!$A$29 -> XXL | B19: =COUNTIFS(PRENDAS!$E$3:$E$202,CATALOGOS!$A$29) -> 0
A20: =CATALOGOS!$A$30 -> XXXL | B20: =COUNTIFS(PRENDAS!$E$3:$E$202,CATALOGOS!$A$30) -> 0
A23: LISTA COMPLETA DE PRENDAS
A24: # | B24: Nombre en prenda | C24: Producto | D24: Talla | E24: N° | F24: Color | G24: Género | H24: Corte | I24: Cuello | J24: Personalización
A25: =IF(PRENDAS!$B3="","",PRENDAS!$A3) -> 1 | B25: =IF(PRENDAS!$B3="","",PRENDAS!$B3) -> ANMIX BRENIS | C25: =IF(PRENDAS!$B3="","",PRENDAS!$D3) -> Kit completo | D25: =IF(PRENDAS!$B3="","",PRENDAS!$E3) -> M | E25: =IF(PRENDAS!$B3="","",PRENDAS!$F3) -> 7 | F25: =IF(PRENDAS!$B3="","",PRENDAS!$G3) -> Blanco hueso | G25: =IF(PRENDAS!$B3="","",PRENDAS!$H3) -> Hombre | H25: =IF(PRENDAS!$B3="","",PRENDAS!$I3) -> Recto | I25: =IF(PRENDAS!$B3="","",PRENDAS!$J3) -> Redondo | J25: =IF(PRENDAS!$B3="","",PRENDAS!$P3) -> Nombre de esposa en cuello delantero
A26: =IF(PRENDAS!$B4="","",PRENDAS!$A4) -> 2 | B26: =IF(PRENDAS!$B4="","",PRENDAS!$B4) -> J. HUANCAS | C26: =IF(PRENDAS!$B4="","",PRENDAS!$D4) -> Kit completo | D26: =IF(PRENDAS!$B4="","",PRENDAS!$E4) -> M | E26: =IF(PRENDAS!$B4="","",PRENDAS!$F4) -> 7 | F26: =IF(PRENDAS!$B4="","",PRENDAS!$G4) -> Blanco hueso | G26: =IF(PRENDAS!$B4="","",PRENDAS!$H4) -> Hombre | H26: =IF(PRENDAS!$B4="","",PRENDAS!$I4) -> Recto | I26: =IF(PRENDAS!$B4="","",PRENDAS!$J4) -> Redondo | J26: =IF(PRENDAS!$B4="","",PRENDAS!$P4)
A27: =IF(PRENDAS!$B5="","",PRENDAS!$A5) -> 3 | B27: =IF(PRENDAS!$B5="","",PRENDAS!$B5) -> BANCES | C27: =IF(PRENDAS!$B5="","",PRENDAS!$D5) -> Kit completo | D27: =IF(PRENDAS!$B5="","",PRENDAS!$E5) -> M | E27: =IF(PRENDAS!$B5="","",PRENDAS!$F5) -> 17 | F27: =IF(PRENDAS!$B5="","",PRENDAS!$G5) -> Blanco hueso | G27: =IF(PRENDAS!$B5="","",PRENDAS!$H5) -> Hombre | H27: =IF(PRENDAS!$B5="","",PRENDAS!$I5) -> Recto | I27: =IF(PRENDAS!$B5="","",PRENDAS!$J5) -> Redondo | J27: =IF(PRENDAS!$B5="","",PRENDAS!$P5)
A28: =IF(PRENDAS!$B6="","",PRENDAS!$A6) -> 4 | B28: =IF(PRENDAS!$B6="","",PRENDAS!$B6) -> VENTURA | C28: =IF(PRENDAS!$B6="","",PRENDAS!$D6) -> Kit completo | D28: =IF(PRENDAS!$B6="","",PRENDAS!$E6) -> M | E28: =IF(PRENDAS!$B6="","",PRENDAS!$F6) -> 9 | F28: =IF(PRENDAS!$B6="","",PRENDAS!$G6) -> Blanco hueso | G28: =IF(PRENDAS!$B6="","",PRENDAS!$H6) -> Hombre | H28: =IF(PRENDAS!$B6="","",PRENDAS!$I6) -> Recto | I28: =IF(PRENDAS!$B6="","",PRENDAS!$J6) -> Redondo | J28: =IF(PRENDAS!$B6="","",PRENDAS!$P6)
A29: =IF(PRENDAS!$B7="","",PRENDAS!$A7) -> 5 | B29: =IF(PRENDAS!$B7="","",PRENDAS!$B7) -> JHEINER | C29: =IF(PRENDAS!$B7="","",PRENDAS!$D7) -> Kit completo | D29: =IF(PRENDAS!$B7="","",PRENDAS!$E7) -> M | E29: =IF(PRENDAS!$B7="","",PRENDAS!$F7) -> 12 | F29: =IF(PRENDAS!$B7="","",PRENDAS!$G7) -> Blanco hueso | G29: =IF(PRENDAS!$B7="","",PRENDAS!$H7) -> Hombre | H29: =IF(PRENDAS!$B7="","",PRENDAS!$I7) -> Recto | I29: =IF(PRENDAS!$B7="","",PRENDAS!$J7) -> Redondo | J29: =IF(PRENDAS!$B7="","",PRENDAS!$P7)
A30: =IF(PRENDAS!$B8="","",PRENDAS!$A8) -> 6 | B30: =IF(PRENDAS!$B8="","",PRENDAS!$B8) -> JUAN R. | C30: =IF(PRENDAS!$B8="","",PRENDAS!$D8) -> Kit completo | D30: =IF(PRENDAS!$B8="","",PRENDAS!$E8) -> M | E30: =IF(PRENDAS!$B8="","",PRENDAS!$F8) -> 12 | F30: =IF(PRENDAS!$B8="","",PRENDAS!$G8) -> Blanco hueso | G30: =IF(PRENDAS!$B8="","",PRENDAS!$H8) -> Hombre | H30: =IF(PRENDAS!$B8="","",PRENDAS!$I8) -> Recto | I30: =IF(PRENDAS!$B8="","",PRENDAS!$J8) -> Redondo | J30: =IF(PRENDAS!$B8="","",PRENDAS!$P8) -> JUAN R. nombre principal; KALESSI en cuello delantero; JOHNATAN manga izquierda; DIEGO manga derecha
A31: =IF(PRENDAS!$B9="","",PRENDAS!$A9) -> 7 | B31: =IF(PRENDAS!$B9="","",PRENDAS!$B9) -> JORGE C. | C31: =IF(PRENDAS!$B9="","",PRENDAS!$D9) -> Kit completo | D31: =IF(PRENDAS!$B9="","",PRENDAS!$E9) -> M | E31: =IF(PRENDAS!$B9="","",PRENDAS!$F9) -> 7 | F31: =IF(PRENDAS!$B9="","",PRENDAS!$G9) -> Blanco hueso | G31: =IF(PRENDAS!$B9="","",PRENDAS!$H9) -> Hombre | H31: =IF(PRENDAS!$B9="","",PRENDAS!$I9) -> Recto | I31: =IF(PRENDAS!$B9="","",PRENDAS!$J9) -> Redondo | J31: =IF(PRENDAS!$B9="","",PRENDAS!$P9)
A32: =IF(PRENDAS!$B10="","",PRENDAS!$A10) -> 8 | B32: =IF(PRENDAS!$B10="","",PRENDAS!$B10) -> C. ACOSTA | C32: =IF(PRENDAS!$B10="","",PRENDAS!$D10) -> Kit completo | D32: =IF(PRENDAS!$B10="","",PRENDAS!$E10) -> M | E32: =IF(PRENDAS!$B10="","",PRENDAS!$F10) -> 10 | F32: =IF(PRENDAS!$B10="","",PRENDAS!$G10) -> Blanco hueso | G32: =IF(PRENDAS!$B10="","",PRENDAS!$H10) -> Hombre | H32: =IF(PRENDAS!$B10="","",PRENDAS!$I10) -> Recto | I32: =IF(PRENDAS!$B10="","",PRENDAS!$J10) -> Redondo | J32: =IF(PRENDAS!$B10="","",PRENDAS!$P10)
A33: =IF(PRENDAS!$B11="","",PRENDAS!$A11) -> 9 | B33: =IF(PRENDAS!$B11="","",PRENDAS!$B11) -> LADINES | C33: =IF(PRENDAS!$B11="","",PRENDAS!$D11) -> Kit completo | D33: =IF(PRENDAS!$B11="","",PRENDAS!$E11) -> L | E33: =IF(PRENDAS!$B11="","",PRENDAS!$F11) -> 3 | F33: =IF(PRENDAS!$B11="","",PRENDAS!$G11) -> Blanco hueso | G33: =IF(PRENDAS!$B11="","",PRENDAS!$H11) -> Hombre | H33: =IF(PRENDAS!$B11="","",PRENDAS!$I11) -> Recto | I33: =IF(PRENDAS!$B11="","",PRENDAS!$J11) -> Redondo | J33: =IF(PRENDAS!$B11="","",PRENDAS!$P11)
A34: =IF(PRENDAS!$B12="","",PRENDAS!$A12) -> 10 | B34: =IF(PRENDAS!$B12="","",PRENDAS!$B12) -> GUSTAVO R. | C34: =IF(PRENDAS!$B12="","",PRENDAS!$D12) -> Kit completo | D34: =IF(PRENDAS!$B12="","",PRENDAS!$E12) -> L | E34: =IF(PRENDAS!$B12="","",PRENDAS!$F12) -> 11 | F34: =IF(PRENDAS!$B12="","",PRENDAS!$G12) -> Blanco hueso | G34: =IF(PRENDAS!$B12="","",PRENDAS!$H12) -> Hombre | H34: =IF(PRENDAS!$B12="","",PRENDAS!$I12) -> Recto | I34: =IF(PRENDAS!$B12="","",PRENDAS!$J12) -> Redondo | J34: =IF(PRENDAS!$B12="","",PRENDAS!$P12)
A35: =IF(PRENDAS!$B13="","",PRENDAS!$A13) -> 11 | B35: =IF(PRENDAS!$B13="","",PRENDAS!$B13) -> CALDERON | C35: =IF(PRENDAS!$B13="","",PRENDAS!$D13) -> Kit completo | D35: =IF(PRENDAS!$B13="","",PRENDAS!$E13) -> L | E35: =IF(PRENDAS!$B13="","",PRENDAS!$F13) -> 14 | F35: =IF(PRENDAS!$B13="","",PRENDAS!$G13) -> Blanco hueso | G35: =IF(PRENDAS!$B13="","",PRENDAS!$H13) -> Hombre | H35: =IF(PRENDAS!$B13="","",PRENDAS!$I13) -> Recto | I35: =IF(PRENDAS!$B13="","",PRENDAS!$J13) -> Redondo | J35: =IF(PRENDAS!$B13="","",PRENDAS!$P13)
A36: =IF(PRENDAS!$B14="","",PRENDAS!$A14) -> 12 | B36: =IF(PRENDAS!$B14="","",PRENDAS!$B14) -> ALAN F. | C36: =IF(PRENDAS!$B14="","",PRENDAS!$D14) -> Kit completo | D36: =IF(PRENDAS!$B14="","",PRENDAS!$E14) -> L | E36: =IF(PRENDAS!$B14="","",PRENDAS!$F14) -> 8 | F36: =IF(PRENDAS!$B14="","",PRENDAS!$G14) -> Blanco hueso | G36: =IF(PRENDAS!$B14="","",PRENDAS!$H14) -> Hombre | H36: =IF(PRENDAS!$B14="","",PRENDAS!$I14) -> Recto | I36: =IF(PRENDAS!$B14="","",PRENDAS!$J14) -> Redondo | J36: =IF(PRENDAS!$B14="","",PRENDAS!$P14)
... A224: =IF(PRENDAS!$B202="","",PRENDAS!$A202) | B224: =IF(PRENDAS!$B202="","",PRENDAS!$B202) | C224: =IF(PRENDAS!$B202="","",PRENDAS!$D202) | D224: =IF(PRENDAS!$B202="","",PRENDAS!$E202) | E224: =IF(PRENDAS!$B202="","",PRENDAS!$F202) | F224: =IF(PRENDAS!$B202="","",PRENDAS!$G202) | G224: =IF(PRENDAS!$B202="","",PRENDAS!$H202) | H224: =IF(PRENDAS!$B202="","",PRENDAS!$I202) | I224: =IF(PRENDAS!$B202="","",PRENDAS!$J202) | J224: =IF(PRENDAS!$B202="","",PRENDAS!$P202)

Sheet FICHA_DISENO
A1: FICHA PARA DISEÑO Y PRODUCCIÓN — sin información de precios
A2: =CONCATENATE("Pedido ",PEDIDO!$B$5," · ",PEDIDO!$B$7," · versión ",PEDIDO!$B$6," · entrega ",PEDIDO!$F$9) -> Pedido SUB-000842 · PROMO 2002 · versión 4 · entrega 2026-08-18
A4: ESPECIFICACIÓN TÉCNICA
A5: Tela principal | C5: =IF(PEDIDO!$B$15="","—",PEDIDO!$B$15) -> Win Fresh | F5: Manga | H5: =IF(PEDIDO!$F$15="","—",PEDIDO!$F$15) -> Corta
A6: Cuello hombres | C6: =IF(PEDIDO!$B$16="","—",PEDIDO!$B$16) -> Redondo | F6: Cuello damas | H6: =IF(PEDIDO!$F$16="","—",PEDIDO!$F$16) -> Redondo
A7: Corte hombres | C7: =IF(PEDIDO!$B$17="","—",PEDIDO!$B$17) -> Recto | F7: Corte damas | H7: =IF(PEDIDO!$F$17="","—",PEDIDO!$F$17) -> Entallado
A8: Rib en cuello | C8: =IF(PEDIDO!$B$18="","—",PEDIDO!$B$18) -> Sí | F8: Rib en mangas | H8: =IF(PEDIDO!$F$18="","—",PEDIDO!$F$18) -> No
A9: Acabado de escudos | C9: =IF(PEDIDO!$B$19="","—",PEDIDO!$B$19) -> Sublimado | F9: Tela del short | H9: =IF(PEDIDO!$F$19="","—",PEDIDO!$F$19) -> Win Fresh
A10: Versión del mockup | C10: =IF(PEDIDO!$B$13="","—",PEDIDO!$B$13) -> v4 | F10: Aprobado el | H10: =IF(PEDIDO!$F$13="","—",PEDIDO!$F$13) -> 2026-08-07
A12: COLORES — usar el código, no el nombre
A13: =IF(PEDIDO!$A$23="","",PEDIDO!$A$23) -> Blanco hueso | C13: =IF(PEDIDO!$B$23="","",PEDIDO!$B$23) -> #F7F4F2 | F13: =IF(PEDIDO!$C$23="","",PEDIDO!$C$23) -> PENDIENTE — el pedido real nunca tuvo código
A14: =IF(PEDIDO!$A$24="","",PEDIDO!$A$24) -> Azul | C14: =IF(PEDIDO!$B$24="","",PEDIDO!$B$24) -> #2B4E7A | F14: =IF(PEDIDO!$C$24="","",PEDIDO!$C$24) -> PENDIENTE — el pedido real nunca tuvo código
A15: =IF(PEDIDO!$A$25="","",PEDIDO!$A$25) | C15: =IF(PEDIDO!$B$25="","",PEDIDO!$B$25) | F15: =IF(PEDIDO!$C$25="","",PEDIDO!$C$25)
A16: =IF(PEDIDO!$A$26="","",PEDIDO!$A$26) | C16: =IF(PEDIDO!$B$26="","",PEDIDO!$B$26) | F16: =IF(PEDIDO!$C$26="","",PEDIDO!$C$26)
A17: =IF(PEDIDO!$A$27="","",PEDIDO!$A$27) | C17: =IF(PEDIDO!$B$27="","",PEDIDO!$B$27) | F17: =IF(PEDIDO!$C$27="","",PEDIDO!$C$27)
A18: =IF(PEDIDO!$A$28="","",PEDIDO!$A$28) | C18: =IF(PEDIDO!$B$28="","",PEDIDO!$B$28) | F18: =IF(PEDIDO!$C$28="","",PEDIDO!$C$28)
A20: UBICACIONES Y TEXTO LITERAL — copiar, no volver a escribir
A21: =PEDIDO!$A$33 -> Pecho / delantero | C21: =IF(PEDIDO!$B$33="","",PEDIDO!$B$33) -> Sí | D21: =IF(PEDIDO!$C$33="","",PEDIDO!$C$33) -> Texto "PROMO 2002", insignia del colegio bordada y sponsors correspondientes
A22: =PEDIDO!$A$34 -> Espalda | C22: =IF(PEDIDO!$B$34="","",PEDIDO!$B$34) -> Sí | D22: =IF(PEDIDO!$C$34="","",PEDIDO!$C$34) -> Nombre, número y sponsor
A23: =PEDIDO!$A$35 -> Cuello delantero | C23: =IF(PEDIDO!$B$35="","",PEDIDO!$B$35) -> No | D23: =IF(PEDIDO!$C$35="","",PEDIDO!$C$35)
A24: =PEDIDO!$A$36 -> Cuello posterior | C24: =IF(PEDIDO!$B$36="","",PEDIDO!$B$36) -> No | D24: =IF(PEDIDO!$C$36="","",PEDIDO!$C$36)
A25: =PEDIDO!$A$37 -> Manga izquierda | C25: =IF(PEDIDO!$B$37="","",PEDIDO!$B$37) -> Sí | D25: =IF(PEDIDO!$C$37="","",PEDIDO!$C$37) -> Copa y texto "COPA 2026"
A26: =PEDIDO!$A$38 -> Manga derecha | C26: =IF(PEDIDO!$B$38="","",PEDIDO!$B$38) -> Sí | D26: =IF(PEDIDO!$C$38="","",PEDIDO!$C$38) -> Insignia del campeonato
A27: =PEDIDO!$A$39 -> Short delantero | C27: =IF(PEDIDO!$B$39="","",PEDIDO!$B$39) -> Sí | D27: =IF(PEDIDO!$C$39="","",PEDIDO!$C$39) -> Insignia del colegio lado derecho, número lado izquierdo
A28: =PEDIDO!$A$40 -> Short posterior | C28: =IF(PEDIDO!$B$40="","",PEDIDO!$B$40) -> Sí | D28: =IF(PEDIDO!$C$40="","",PEDIDO!$C$40) -> Sponsors correspondientes
A29: =PEDIDO!$A$41 -> Sponsor 1 — texto y teléfono | C29: =IF(PEDIDO!$B$41="","",PEDIDO!$B$41) -> Sí | D29: =IF(PEDIDO!$C$41="","",PEDIDO!$C$41) -> SIN DEFINIR — la confirmación real nunca dijo qué sponsor ni su teléfono
A30: =PEDIDO!$A$42 -> Sponsor 2 — texto y teléfono | C30: =IF(PEDIDO!$B$42="","",PEDIDO!$B$42) -> No | D30: =IF(PEDIDO!$C$42="","",PEDIDO!$C$42)
A32: CANTIDADES PARA PRODUCCIÓN
A33: Camisetas | B33: =SUM(PRENDAS!$W$3:$W$202) -> 28 | D33: Shorts | E33: =SUM(PRENDAS!$X$3:$X$202) -> 17 | G33: Medias | H33: =SUM(PRENDAS!$Y$3:$Y$202) -> 17
A34: Un pedido real se despachó sin las medias porque el resumen no tenía esta línea.
A36: LISTA DE PRENDAS
A37: # | B37: Nombre en prenda | C37: Producto | D37: Talla | E37: N° | F37: Color | G37: Género | H37: Corte | I37: Cuello | J37: Personalización especial
A38: =IF(PRENDAS!$B3="","",PRENDAS!$A3) -> 1 | B38: =IF(PRENDAS!$B3="","",PRENDAS!$B3) -> ANMIX BRENIS | C38: =IF(PRENDAS!$B3="","",PRENDAS!$D3) -> Kit completo | D38: =IF(PRENDAS!$B3="","",PRENDAS!$E3) -> M | E38: =IF(PRENDAS!$B3="","",PRENDAS!$F3) -> 7 | F38: =IF(PRENDAS!$B3="","",PRENDAS!$G3) -> Blanco hueso | G38: =IF(PRENDAS!$B3="","",PRENDAS!$H3) -> Hombre | H38: =IF(PRENDAS!$B3="","",PRENDAS!$I3) -> Recto | I38: =IF(PRENDAS!$B3="","",PRENDAS!$J3) -> Redondo | J38: =IF(PRENDAS!$B3="","",PRENDAS!$P3) -> Nombre de esposa en cuello delantero
A39: =IF(PRENDAS!$B4="","",PRENDAS!$A4) -> 2 | B39: =IF(PRENDAS!$B4="","",PRENDAS!$B4) -> J. HUANCAS | C39: =IF(PRENDAS!$B4="","",PRENDAS!$D4) -> Kit completo | D39: =IF(PRENDAS!$B4="","",PRENDAS!$E4) -> M | E39: =IF(PRENDAS!$B4="","",PRENDAS!$F4) -> 7 | F39: =IF(PRENDAS!$B4="","",PRENDAS!$G4) -> Blanco hueso | G39: =IF(PRENDAS!$B4="","",PRENDAS!$H4) -> Hombre | H39: =IF(PRENDAS!$B4="","",PRENDAS!$I4) -> Recto | I39: =IF(PRENDAS!$B4="","",PRENDAS!$J4) -> Redondo | J39: =IF(PRENDAS!$B4="","",PRENDAS!$P4)
A40: =IF(PRENDAS!$B5="","",PRENDAS!$A5) -> 3 | B40: =IF(PRENDAS!$B5="","",PRENDAS!$B5) -> BANCES | C40: =IF(PRENDAS!$B5="","",PRENDAS!$D5) -> Kit completo | D40: =IF(PRENDAS!$B5="","",PRENDAS!$E5) -> M | E40: =IF(PRENDAS!$B5="","",PRENDAS!$F5) -> 17 | F40: =IF(PRENDAS!$B5="","",PRENDAS!$G5) -> Blanco hueso | G40: =IF(PRENDAS!$B5="","",PRENDAS!$H5) -> Hombre | H40: =IF(PRENDAS!$B5="","",PRENDAS!$I5) -> Recto | I40: =IF(PRENDAS!$B5="","",PRENDAS!$J5) -> Redondo | J40: =IF(PRENDAS!$B5="","",PRENDAS!$P5)
A41: =IF(PRENDAS!$B6="","",PRENDAS!$A6) -> 4 | B41: =IF(PRENDAS!$B6="","",PRENDAS!$B6) -> VENTURA | C41: =IF(PRENDAS!$B6="","",PRENDAS!$D6) -> Kit completo | D41: =IF(PRENDAS!$B6="","",PRENDAS!$E6) -> M | E41: =IF(PRENDAS!$B6="","",PRENDAS!$F6) -> 9 | F41: =IF(PRENDAS!$B6="","",PRENDAS!$G6) -> Blanco hueso | G41: =IF(PRENDAS!$B6="","",PRENDAS!$H6) -> Hombre | H41: =IF(PRENDAS!$B6="","",PRENDAS!$I6) -> Recto | I41: =IF(PRENDAS!$B6="","",PRENDAS!$J6) -> Redondo | J41: =IF(PRENDAS!$B6="","",PRENDAS!$P6)
A42: =IF(PRENDAS!$B7="","",PRENDAS!$A7) -> 5 | B42: =IF(PRENDAS!$B7="","",PRENDAS!$B7) -> JHEINER | C42: =IF(PRENDAS!$B7="","",PRENDAS!$D7) -> Kit completo | D42: =IF(PRENDAS!$B7="","",PRENDAS!$E7) -> M | E42: =IF(PRENDAS!$B7="","",PRENDAS!$F7) -> 12 | F42: =IF(PRENDAS!$B7="","",PRENDAS!$G7) -> Blanco hueso | G42: =IF(PRENDAS!$B7="","",PRENDAS!$H7) -> Hombre | H42: =IF(PRENDAS!$B7="","",PRENDAS!$I7) -> Recto | I42: =IF(PRENDAS!$B7="","",PRENDAS!$J7) -> Redondo | J42: =IF(PRENDAS!$B7="","",PRENDAS!$P7)
A43: =IF(PRENDAS!$B8="","",PRENDAS!$A8) -> 6 | B43: =IF(PRENDAS!$B8="","",PRENDAS!$B8) -> JUAN R. | C43: =IF(PRENDAS!$B8="","",PRENDAS!$D8) -> Kit completo | D43: =IF(PRENDAS!$B8="","",PRENDAS!$E8) -> M | E43: =IF(PRENDAS!$B8="","",PRENDAS!$F8) -> 12 | F43: =IF(PRENDAS!$B8="","",PRENDAS!$G8) -> Blanco hueso | G43: =IF(PRENDAS!$B8="","",PRENDAS!$H8) -> Hombre | H43: =IF(PRENDAS!$B8="","",PRENDAS!$I8) -> Recto | I43: =IF(PRENDAS!$B8="","",PRENDAS!$J8) -> Redondo | J43: =IF(PRENDAS!$B8="","",PRENDAS!$P8) -> JUAN R. nombre principal; KALESSI en cuello delantero; JOHNATAN manga izquierda; DIEGO manga derecha
A44: =IF(PRENDAS!$B9="","",PRENDAS!$A9) -> 7 | B44: =IF(PRENDAS!$B9="","",PRENDAS!$B9) -> JORGE C. | C44: =IF(PRENDAS!$B9="","",PRENDAS!$D9) -> Kit completo | D44: =IF(PRENDAS!$B9="","",PRENDAS!$E9) -> M | E44: =IF(PRENDAS!$B9="","",PRENDAS!$F9) -> 7 | F44: =IF(PRENDAS!$B9="","",PRENDAS!$G9) -> Blanco hueso | G44: =IF(PRENDAS!$B9="","",PRENDAS!$H9) -> Hombre | H44: =IF(PRENDAS!$B9="","",PRENDAS!$I9) -> Recto | I44: =IF(PRENDAS!$B9="","",PRENDAS!$J9) -> Redondo | J44: =IF(PRENDAS!$B9="","",PRENDAS!$P9)
A45: =IF(PRENDAS!$B10="","",PRENDAS!$A10) -> 8 | B45: =IF(PRENDAS!$B10="","",PRENDAS!$B10) -> C. ACOSTA | C45: =IF(PRENDAS!$B10="","",PRENDAS!$D10) -> Kit completo | D45: =IF(PRENDAS!$B10="","",PRENDAS!$E10) -> M | E45: =IF(PRENDAS!$B10="","",PRENDAS!$F10) -> 10 | F45: =IF(PRENDAS!$B10="","",PRENDAS!$G10) -> Blanco hueso | G45: =IF(PRENDAS!$B10="","",PRENDAS!$H10) -> Hombre | H45: =IF(PRENDAS!$B10="","",PRENDAS!$I10) -> Recto | I45: =IF(PRENDAS!$B10="","",PRENDAS!$J10) -> Redondo | J45: =IF(PRENDAS!$B10="","",PRENDAS!$P10)
A46: =IF(PRENDAS!$B11="","",PRENDAS!$A11) -> 9 | B46: =IF(PRENDAS!$B11="","",PRENDAS!$B11) -> LADINES | C46: =IF(PRENDAS!$B11="","",PRENDAS!$D11) -> Kit completo | D46: =IF(PRENDAS!$B11="","",PRENDAS!$E11) -> L | E46: =IF(PRENDAS!$B11="","",PRENDAS!$F11) -> 3 | F46: =IF(PRENDAS!$B11="","",PRENDAS!$G11) -> Blanco hueso | G46: =IF(PRENDAS!$B11="","",PRENDAS!$H11) -> Hombre | H46: =IF(PRENDAS!$B11="","",PRENDAS!$I11) -> Recto | I46: =IF(PRENDAS!$B11="","",PRENDAS!$J11) -> Redondo | J46: =IF(PRENDAS!$B11="","",PRENDAS!$P11)
A47: =IF(PRENDAS!$B12="","",PRENDAS!$A12) -> 10 | B47: =IF(PRENDAS!$B12="","",PRENDAS!$B12) -> GUSTAVO R. | C47: =IF(PRENDAS!$B12="","",PRENDAS!$D12) -> Kit completo | D47: =IF(PRENDAS!$B12="","",PRENDAS!$E12) -> L | E47: =IF(PRENDAS!$B12="","",PRENDAS!$F12) -> 11 | F47: =IF(PRENDAS!$B12="","",PRENDAS!$G12) -> Blanco hueso | G47: =IF(PRENDAS!$B12="","",PRENDAS!$H12) -> Hombre | H47: =IF(PRENDAS!$B12="","",PRENDAS!$I12) -> Recto | I47: =IF(PRENDAS!$B12="","",PRENDAS!$J12) -> Redondo | J47: =IF(PRENDAS!$B12="","",PRENDAS!$P12)
A48: =IF(PRENDAS!$B13="","",PRENDAS!$A13) -> 11 | B48: =IF(PRENDAS!$B13="","",PRENDAS!$B13) -> CALDERON | C48: =IF(PRENDAS!$B13="","",PRENDAS!$D13) -> Kit completo | D48: =IF(PRENDAS!$B13="","",PRENDAS!$E13) -> L | E48: =IF(PRENDAS!$B13="","",PRENDAS!$F13) -> 14 | F48: =IF(PRENDAS!$B13="","",PRENDAS!$G13) -> Blanco hueso | G48: =IF(PRENDAS!$B13="","",PRENDAS!$H13) -> Hombre | H48: =IF(PRENDAS!$B13="","",PRENDAS!$I13) -> Recto | I48: =IF(PRENDAS!$B13="","",PRENDAS!$J13) -> Redondo | J48: =IF(PRENDAS!$B13="","",PRENDAS!$P13)
A49: =IF(PRENDAS!$B14="","",PRENDAS!$A14) -> 12 | B49: =IF(PRENDAS!$B14="","",PRENDAS!$B14) -> ALAN F. | C49: =IF(PRENDAS!$B14="","",PRENDAS!$D14) -> Kit completo | D49: =IF(PRENDAS!$B14="","",PRENDAS!$E14) -> L | E49: =IF(PRENDAS!$B14="","",PRENDAS!$F14) -> 8 | F49: =IF(PRENDAS!$B14="","",PRENDAS!$G14) -> Blanco hueso | G49: =IF(PRENDAS!$B14="","",PRENDAS!$H14) -> Hombre | H49: =IF(PRENDAS!$B14="","",PRENDAS!$I14) -> Recto | I49: =IF(PRENDAS!$B14="","",PRENDAS!$J14) -> Redondo | J49: =IF(PRENDAS!$B14="","",PRENDAS!$P14)
... A237: =IF(PRENDAS!$B202="","",PRENDAS!$A202) | B237: =IF(PRENDAS!$B202="","",PRENDAS!$B202) | C237: =IF(PRENDAS!$B202="","",PRENDAS!$D202) | D237: =IF(PRENDAS!$B202="","",PRENDAS!$E202) | E237: =IF(PRENDAS!$B202="","",PRENDAS!$F202) | F237: =IF(PRENDAS!$B202="","",PRENDAS!$G202) | G237: =IF(PRENDAS!$B202="","",PRENDAS!$H202) | H237: =IF(PRENDAS!$B202="","",PRENDAS!$I202) | I237: =IF(PRENDAS!$B202="","",PRENDAS!$J202) | J237: =IF(PRENDAS!$B202="","",PRENDAS!$P202)

Sheet MEDIDAS
A1: MEDIDAS DE NESTING — la llena el diseñador después de organizar las piezas
A2: =CONCATENATE("Pedido ",PEDIDO!$B$5," · ",PEDIDO!$B$7) -> Pedido SUB-000842 · PROMO 2002
A3: Un nesting puede mezclar piezas de varios pedidos. Si es así, indica a qué pedido corresponde cada parte.
A5: Tela | B5: Parte | C5: Ancho (cm) | D5: Largo (cm) | E5: Pedido al que corresponde | F5: Metros lineales | G5: Costo impresión | H5: Área impresa (m²) | I5: Archivo TIF sugerido
F6: =IF($D6="","",$D6/100) | G6: =IF($D6="","",ROUND($F6*CATALOGOS!$B$80,2)) | H6: =IF($D6="","",ROUND($F6*CATALOGOS!$B$79,2)) | I6: =IF($D6="","",CONCATENATE("SUBLITEX_",IF($E6="",PEDIDO!$B$7,$E6),"_",UPPER($A6),"_180x",$D6,"_parte",$B6,".tif"))
F7: =IF($D7="","",$D7/100) | G7: =IF($D7="","",ROUND($F7*CATALOGOS!$B$80,2)) | H7: =IF($D7="","",ROUND($F7*CATALOGOS!$B$79,2)) | I7: =IF($D7="","",CONCATENATE("SUBLITEX_",IF($E7="",PEDIDO!$B$7,$E7),"_",UPPER($A7),"_180x",$D7,"_parte",$B7,".tif"))
F8: =IF($D8="","",$D8/100) | G8: =IF($D8="","",ROUND($F8*CATALOGOS!$B$80,2)) | H8: =IF($D8="","",ROUND($F8*CATALOGOS!$B$79,2)) | I8: =IF($D8="","",CONCATENATE("SUBLITEX_",IF($E8="",PEDIDO!$B$7,$E8),"_",UPPER($A8),"_180x",$D8,"_parte",$B8,".tif"))
F9: =IF($D9="","",$D9/100) | G9: =IF($D9="","",ROUND($F9*CATALOGOS!$B$80,2)) | H9: =IF($D9="","",ROUND($F9*CATALOGOS!$B$79,2)) | I9: =IF($D9="","",CONCATENATE("SUBLITEX_",IF($E9="",PEDIDO!$B$7,$E9),"_",UPPER($A9),"_180x",$D9,"_parte",$B9,".tif"))
F10: =IF($D10="","",$D10/100) | G10: =IF($D10="","",ROUND($F10*CATALOGOS!$B$80,2)) | H10: =IF($D10="","",ROUND($F10*CATALOGOS!$B$79,2)) | I10: =IF($D10="","",CONCATENATE("SUBLITEX_",IF($E10="",PEDIDO!$B$7,$E10),"_",UPPER($A10),"_180x",$D10,"_parte",$B10,".tif"))
F11: =IF($D11="","",$D11/100) | G11: =IF($D11="","",ROUND($F11*CATALOGOS!$B$80,2)) | H11: =IF($D11="","",ROUND($F11*CATALOGOS!$B$79,2)) | I11: =IF($D11="","",CONCATENATE("SUBLITEX_",IF($E11="",PEDIDO!$B$7,$E11),"_",UPPER($A11),"_180x",$D11,"_parte",$B11,".tif"))
F12: =IF($D12="","",$D12/100) | G12: =IF($D12="","",ROUND($F12*CATALOGOS!$B$80,2)) | H12: =IF($D12="","",ROUND($F12*CATALOGOS!$B$79,2)) | I12: =IF($D12="","",CONCATENATE("SUBLITEX_",IF($E12="",PEDIDO!$B$7,$E12),"_",UPPER($A12),"_180x",$D12,"_parte",$B12,".tif"))
F13: =IF($D13="","",$D13/100) | G13: =IF($D13="","",ROUND($F13*CATALOGOS!$B$80,2)) | H13: =IF($D13="","",ROUND($F13*CATALOGOS!$B$79,2)) | I13: =IF($D13="","",CONCATENATE("SUBLITEX_",IF($E13="",PEDIDO!$B$7,$E13),"_",UPPER($A13),"_180x",$D13,"_parte",$B13,".tif"))
F14: =IF($D14="","",$D14/100) | G14: =IF($D14="","",ROUND($F14*CATALOGOS!$B$80,2)) | H14: =IF($D14="","",ROUND($F14*CATALOGOS!$B$79,2)) | I14: =IF($D14="","",CONCATENATE("SUBLITEX_",IF($E14="",PEDIDO!$B$7,$E14),"_",UPPER($A14),"_180x",$D14,"_parte",$B14,".tif"))
F15: =IF($D15="","",$D15/100) | G15: =IF($D15="","",ROUND($F15*CATALOGOS!$B$80,2)) | H15: =IF($D15="","",ROUND($F15*CATALOGOS!$B$79,2)) | I15: =IF($D15="","",CONCATENATE("SUBLITEX_",IF($E15="",PEDIDO!$B$7,$E15),"_",UPPER($A15),"_180x",$D15,"_parte",$B15,".tif"))
F16: =IF($D16="","",$D16/100) | G16: =IF($D16="","",ROUND($F16*CATALOGOS!$B$80,2)) | H16: =IF($D16="","",ROUND($F16*CATALOGOS!$B$79,2)) | I16: =IF($D16="","",CONCATENATE("SUBLITEX_",IF($E16="",PEDIDO!$B$7,$E16),"_",UPPER($A16),"_180x",$D16,"_parte",$B16,".tif"))
F17: =IF($D17="","",$D17/100) | G17: =IF($D17="","",ROUND($F17*CATALOGOS!$B$80,2)) | H17: =IF($D17="","",ROUND($F17*CATALOGOS!$B$79,2)) | I17: =IF($D17="","",CONCATENATE("SUBLITEX_",IF($E17="",PEDIDO!$B$7,$E17),"_",UPPER($A17),"_180x",$D17,"_parte",$B17,".tif"))
... F25: =IF($D25="","",$D25/100) | G25: =IF($D25="","",ROUND($F25*CATALOGOS!$B$80,2)) | H25: =IF($D25="","",ROUND($F25*CATALOGOS!$B$79,2)) | I25: =IF($D25="","",CONCATENATE("SUBLITEX_",IF($E25="",PEDIDO!$B$7,$E25),"_",UPPER($A25),"_180x",$D25,"_parte",$B25,".tif"))
D27: TOTAL | F27: =SUM(F6:F25) -> 0 | G27: =SUM(G6:G25) -> 0 | H27: =SUM(H6:H25) -> 0
A29: CONTROL DE ARCHIVOS Y TELA
A30: Metros lineales de este pedido | D30: =SUMIFS($F$6:$F$25,$E$6:$E$25,PEDIDO!$B$7)+SUMIFS($F$6:$F$25,$E$6:$E$25,"") -> 0
A31: Costo de impresión de este pedido | D31: =ROUND(D30*CATALOGOS!$B$80,2) -> 0
A32: Cantidad de archivos TIF entregados | D32: 0
A33: Fecha de entrega de archivos
A35: Un archivo de más de 5 m de largo conviene partirlo. El ancho siempre es 1.80 m; lo que varía es el largo.
